Workbook

Sheet MARZO
A1: MARZO 2025
A2: FECHA | B2: No DOCUMENTO | C2: CONSECUTIVO | D2: NIT | E2: RAZON SOCIAL | F2: PRIMER NOMBRE | G2: SEGUNDO NOMBRE | H2: PRIMER APELLIDO | I2: SEGUNDO APELLIDO | J2: DIRECCION | K2: TELEFONO | L2: CORREO | M2: VALOR | N2: TIPO DE GASTO
A3: 45718 | B3: 3963 | D3: =IFERROR(VLOOKUP($E3,'BASE DE DATOS'!$A:$I,2,0)," ") -> 66929745 | E3: ='BASE DE DATOS'!$A$111 -> POLLOS EL SABOR | F3: =IFERROR(VLOOKUP($D3,'BASE DE DATOS'!$B:$I,2,0),0) -> MARTHA | G3: =IFERROR(VLOOKUP($D3,'BASE DE DATOS'!$B:$I,3,0),0) -> 0 | H3: =IFERROR(VLOOKUP($D3,'BASE DE DATOS'!$B:$I,4,0),0) -> 0 | I3: =IFERROR(VLOOKUP($D3,'BASE DE DATOS'!$B:$I,5,0),0) -> 0 | J3: =IFERROR(VLOOKUP($D3,'BASE DE DATOS'!$B:$I,6,0),0) -> CL 8 12 10 | K3: =IFERROR(VLOOKUP($D3,'BASE DE DATOS'!$B:$I,7,0),0) -> 3017199935 | L3: =IFERROR(VLOOKUP($D3,'BASE DE DATOS'!$B:$I,8,0),0) -> 0 | M3: 481900 | N3: COSTO
A4: 45720 | B4: 0 | D4: =IFERROR(VLOOKUP($E4,'BASE DE DATOS'!$A:$I,2,0)," ") -> 94303413 | E4: ='BASE DE DATOS'!$A$19 -> COLANTA | F4: =IFERROR(VLOOKUP($D4,'BASE DE DATOS'!$B:$I,2,0),0) -> GUSTAVO | G4: =IFERROR(VLOOKUP($D4,'BASE DE DATOS'!$B:$I,3,0),0) -> ADOLFO | H4: =IFERROR(VLOOKUP($D4,'BASE DE DATOS'!$B:$I,4,0),0) -> CAMPO | I4: =IFERROR(VLOOKUP($D4,'BASE DE DATOS'!$B:$I,5,0),0) -> TORRES | J4: =IFERROR(VLOOKUP($D4,'BASE DE DATOS'!$B:$I,6,0),0) -> CL 6 13 04 | K4: =IFERROR(VLOOKUP($D4,'BASE DE DATOS'!$B:$I,7,0),0) -> 3136595942 | L4: =IFERROR(VLOOKUP($D4,'BASE DE DATOS'!$B:$I,8,0),0) -> 0 | M4: 490000 | N4: COSTO
A5: 45692 | B5: 0 | D5: =IFERROR(VLOOKUP($E5,'BASE DE DATOS'!$A:$I,2,0)," ") -> 0 | E5: ='BASE DE DATOS'!$A$3 -> aguacates | F5: =IFERROR(VLOOKUP($D5,'BASE DE DATOS'!$B:$I,2,0),0) -> 0 | G5: =IFERROR(VLOOKUP($D5,'BASE DE DATOS'!$B:$I,3,0),0) -> 0 | H5: =IFERROR(VLOOKUP($D5,'BASE DE DATOS'!$B:$I,4,0),0) -> 0 | I5: =IFERROR(VLOOKUP($D5,'BASE DE DATOS'!$B:$I,5,0),0) -> 0 | J5: =IFERROR(VLOOKUP($D5,'BASE DE DATOS'!$B:$I,6,0),0) -> 0 | K5: =IFERROR(VLOOKUP($D5,'BASE DE DATOS'!$B:$I,7,0),0) -> 0 | L5: =IFERROR(VLOOKUP($D5,'BASE DE DATOS'!$B:$I,8,0),0) -> 0 | M5: 248000 | N5: COSTO
A6: 45717 | B6: 6991227 | D6: =IFERROR(VLOOKUP($E6,'BASE DE DATOS'!$A:$I,2,0)," ") -> 8150048801 | E6: ='BASE DE DATOS'!$A$143 -> DISTRIBUIDORA TIENDAS Y MARCAS | F6: =IFERROR(VLOOKUP($D6,'BASE DE DATOS'!$B:$I,2,0),0) -> ELIANA | G6: =IFERROR(VLOOKUP($D6,'BASE DE DATOS'!$B:$I,3,0),0) -> MARIA | H6: =IFERROR(VLOOKUP($D6,'BASE DE DATOS'!$B:$I,4,0),0) -> 0 | I6: =IFERROR(VLOOKUP($D6,'BASE DE DATOS'!$B:$I,5,0),0) -> 0 | J6: =IFERROR(VLOOKUP($D6,'BASE DE DATOS'!$B:$I,6,0),0) -> CRA 34 31 35 BOD 2 PALMIRA | K6: =IFERROR(VLOOKUP($D6,'BASE DE DATOS'!$B:$I,7,0),0) -> 3228469553 | L6: =IFERROR(VLOOKUP($D6,'BASE DE DATOS'!$B:$I,8,0),0) -> 0 | M6: 186900 | N6: COSTO
A7: 45717 | B7: 3766 | D7: =IFERROR(VLOOKUP($E7,'BASE DE DATOS'!$A:$I,2,0)," ") -> 66929745 | E7: POLLOS EL SABOR | F7: =IFERROR(VLOOKUP($D7,'BASE DE DATOS'!$B:$I,2,0),0) -> MARTHA | G7: =IFERROR(VLOOKUP($D7,'BASE DE DATOS'!$B:$I,3,0),0) -> 0 | H7: =IFERROR(VLOOKUP($D7,'BASE DE DATOS'!$B:$I,4,0),0) -> 0 | I7: =IFERROR(VLOOKUP($D7,'BASE DE DATOS'!$B:$I,5,0),0) -> 0 | J7: =IFERROR(VLOOKUP($D7,'BASE DE DATOS'!$B:$I,6,0),0) -> CL 8 12 10 | K7: =IFERROR(VLOOKUP($D7,'BASE DE DATOS'!$B:$I,7,0),0) -> 3017199935 | L7: =IFERROR(VLOOKUP($D7,'BASE DE DATOS'!$B:$I,8,0),0) -> 0 | M7: 475600 | N7: COSTO
A8: 45717 | B8: 0 | D8: =IFERROR(VLOOKUP($E8,'BASE DE DATOS'!$A:$I,2,0)," ") -> 0 | E8: ='BASE DE DATOS'!$A$174 -> LECHUGA | F8: =IFERROR(VLOOKUP($D8,'BASE DE DATOS'!$B:$I,2,0),0) -> 0 | G8: =IFERROR(VLOOKUP($D8,'BASE DE DATOS'!$B:$I,3,0),0) -> 0 | H8: =IFERROR(VLOOKUP($D8,'BASE DE DATOS'!$B:$I,4,0),0) -> 0 | I8: =IFERROR(VLOOKUP($D8,'BASE DE DATOS'!$B:$I,5,0),0) -> 0 | J8: =IFERROR(VLOOKUP($D8,'BASE DE DATOS'!$B:$I,6,0),0) -> 0 | K8: =IFERROR(VLOOKUP($D8,'BASE DE DATOS'!$B:$I,7,0),0) -> 0 | L8: =IFERROR(VLOOKUP($D8,'BASE DE DATOS'!$B:$I,8,0),0) -> 0 | M8: 15400 | N8: COSTO
A9: 45717 | B9: 0 | D9: =IFERROR(VLOOKUP($E9,'BASE DE DATOS'!$A:$I,2,0)," ") -> 0 | E9: ='BASE DE DATOS'!$A$58 -> gastos varios caja/ descuadres | F9: =IFERROR(VLOOKUP($D9,'BASE DE DATOS'!$B:$I,2,0),0) -> 0 | G9: =IFERROR(VLOOKUP($D9,'BASE DE DATOS'!$B:$I,3,0),0) -> 0 | H9: =IFERROR(VLOOKUP($D9,'BASE DE DATOS'!$B:$I,4,0),0) -> 0 | I9: =IFERROR(VLOOKUP($D9,'BASE DE DATOS'!$B:$I,5,0),0) -> 0 | J9: =IFERROR(VLOOKUP($D9,'BASE DE DATOS'!$B:$I,6,0),0) -> 0 | K9: =IFERROR(VLOOKUP($D9,'BASE DE DATOS'!$B:$I,7,0),0) -> 0 | L9: =IFERROR(VLOOKUP($D9,'BASE DE DATOS'!$B:$I,8,0),0) -> 0 | M9: 84000 | N9: COSTO
A10: 45718 | B10: 0 | D10: =IFERROR(VLOOKUP($E10,'BASE DE DATOS'!$A:$I,2,0)," ") -> 0 | E10: ='BASE DE DATOS'!$A$176 -> MERCAFRUVER LA ECONOMIA demi pradera | F10: =IFERROR(VLOOKUP($D10,'BASE DE DATOS'!$B:$I,2,0),0) -> 0 | G10: =IFERROR(VLOOKUP($D10,'BASE DE DATOS'!$B:$I,3,0),0) -> 0 | H10: =IFERROR(VLOOKUP($D10,'BASE DE DATOS'!$B:$I,4,0),0) -> 0 | I10: =IFERROR(VLOOKUP($D10,'BASE DE DATOS'!$B:$I,5,0),0) -> 0 | J10: =IFERROR(VLOOKUP($D10,'BASE DE DATOS'!$B:$I,6,0),0) -> 0 | K10: =IFERROR(VLOOKUP($D10,'BASE DE DATOS'!$B:$I,7,0),0) -> 0 | L10: =IFERROR(VLOOKUP($D10,'BASE DE DATOS'!$B:$I,8,0),0) -> 0 | M10: 56000 | N10: COSTO
A11: 45718 | B11: 0 | D11: =IFERROR(VLOOKUP($E11,'BASE DE DATOS'!$A:$I,2,0)," ") -> 0 | E11: gastos varios caja/ descuadres | F11: =IFERROR(VLOOKUP($D11,'BASE DE DATOS'!$B:$I,2,0),0) -> 0 | G11: =IFERROR(VLOOKUP($D11,'BASE DE DATOS'!$B:$I,3,0),0) -> 0 | H11: =IFERROR(VLOOKUP($D11,'BASE DE DATOS'!$B:$I,4,0),0) -> 0 | I11: =IFERROR(VLOOKUP($D11,'BASE DE DATOS'!$B:$I,5,0),0) -> 0 | J11: =IFERROR(VLOOKUP($D11,'BASE DE DATOS'!$B:$I,6,0),0) -> 0 | K11: =IFERROR(VLOOKUP($D11,'BASE DE DATOS'!$B:$I,7,0),0) -> 0 | L11: =IFERROR(VLOOKUP($D11,'BASE DE DATOS'!$B:$I,8,0),0) -> 0 | M11: 3000 | N11: GASTO
A12: 45717 | B12: 18 | D12: =IFERROR(VLOOKUP($E12,'BASE DE DATOS'!$A:$I,2,0)," ") -> 14695845 | E12: ='BASE DE DATOS'!$A$93 -> MERCAFRUVER EL MAYORISTA | F12: =IFERROR(VLOOKUP($D12,'BASE DE DATOS'!$B:$I,2,0),0) -> EDELMIRA | G12: =IFERROR(VLOOKUP($D12,'BASE DE DATOS'!$B:$I,3,0),0) -> 0 | H12: =IFERROR(VLOOKUP($D12,'BASE DE DATOS'!$B:$I,4,0),0) -> MORALES | I12: =IFERROR(VLOOKUP($D12,'BASE DE DATOS'!$B:$I,5,0),0) -> ACOSTA | J12: =IFERROR(VLOOKUP($D12,'BASE DE DATOS'!$B:$I,6,0),0) -> ST 1 MZ 19 VILLAMARINA | K12: =IFERROR(VLOOKUP($D12,'BASE DE DATOS'!$B:$I,7,0),0) -> 3215223609 | L12: =IFERROR(VLOOKUP($D12,'BASE DE DATOS'!$B:$I,8,0),0) -> 0 | M12: 110000 | N12: COSTO
A13: 45721 | B13: 9181514 | D13: =IFERROR(VLOOKUP($E13,'BASE DE DATOS'!$A:$I,2,0)," ") -> 800249860 | E13: ='BASE DE DATOS'!$A$13 -> CELSIA COLOMBIA SA ESP | F13: =IFERROR(VLOOKUP($D13,'BASE DE DATOS'!$B:$I,2,0),0) -> NO TIENE | G13: =IFERROR(VLOOKUP($D13,'BASE DE DATOS'!$B:$I,3,0),0) -> NO TIENE | H13: =IFERROR(VLOOKUP($D13,'BASE DE DATOS'!$B:$I,4,0),0) -> NO TIENE | I13: =IFERROR(VLOOKUP($D13,'BASE DE DATOS'!$B:$I,5,0),0) -> NO TIENE | J13: =IFERROR(VLOOKUP($D13,'BASE DE DATOS'!$B:$I,6,0),0) -> CL 15 29 30 | K13: =IFERROR(VLOOKUP($D13,'BASE DE DATOS'!$B:$I,7,0),0) -> 3210000 | L13: =IFERROR(VLOOKUP($D13,'BASE DE DATOS'!$B:$I,8,0),0) -> servicioalcliente@celsia.com | M13: 508170 | N13: SERVICIOS
A14: 45720 | B14: 0 | D14: =IFERROR(VLOOKUP($E14,'BASE DE DATOS'!$A:$I,2,0)," ") -> 4712068 | E14: ='BASE DE DATOS'!$A$59 -> GERMAN TOVAR | F14: =IFERROR(VLOOKUP($D14,'BASE DE DATOS'!$B:$I,2,0),0) -> GERMAN | G14: =IFERROR(VLOOKUP($D14,'BASE DE DATOS'!$B:$I,3,0),0) -> 0 | H14: =IFERROR(VLOOKUP($D14,'BASE DE DATOS'!$B:$I,4,0),0) -> TOVAR | I14: =IFERROR(VLOOKUP($D14,'BASE DE DATOS'!$B:$I,5,0),0) -> 0 | J14: =IFERROR(VLOOKUP($D14,'BASE DE DATOS'!$B:$I,6,0),0) -> CL 6 15 03 | K14: =IFERROR(VLOOKUP($D14,'BASE DE DATOS'!$B:$I,7,0),0) -> 3168117423 | L14: =IFERROR(VLOOKUP($D14,'BASE DE DATOS'!$B:$I,8,0),0) -> 0 | M14: 600000 | N14: SERVICIOS
A15: 45720 | B15: 0 | D15: =IFERROR(VLOOKUP($E15,'BASE DE DATOS'!$A:$I,2,0)," ") -> 4712068 | E15: ='BASE DE DATOS'!$A$59 -> GERMAN TOVAR | F15: =IFERROR(VLOOKUP($D15,'BASE DE DATOS'!$B:$I,2,0),0) -> GERMAN | G15: =IFERROR(VLOOKUP($D15,'BASE DE DATOS'!$B:$I,3,0),0) -> 0 | H15: =IFERROR(VLOOKUP($D15,'BASE DE DATOS'!$B:$I,4,0),0) -> TOVAR | I15: =IFERROR(VLOOKUP($D15,'BASE DE DATOS'!$B:$I,5,0),0) -> 0 | J15: =IFERROR(VLOOKUP($D15,'BASE DE DATOS'!$B:$I,6,0),0) -> CL 6 15 03 | K15: =IFERROR(VLOOKUP($D15,'BASE DE DATOS'!$B:$I,7,0),0) -> 3168117423 | L15: =IFERROR(VLOOKUP($D15,'BASE DE DATOS'!$B:$I,8,0),0) -> 0 | M15: 600000 | N15: SERVICIOS
A16: 45721 | B16: 4105 | D16: =IFERROR(VLOOKUP($E16,'BASE DE DATOS'!$A:$I,2,0)," ") -> 66929745 | E16: POLLOS EL SABOR | F16: =IFERROR(VLOOKUP($D16,'BASE DE DATOS'!$B:$I,2,0),0) -> MARTHA | G16: =IFERROR(VLOOKUP($D16,'BASE DE DATOS'!$B:$I,3,0),0) -> 0 | H16: =IFERROR(VLOOKUP($D16,'BASE DE DATOS'!$B:$I,4,0),0) -> 0 | I16: =IFERROR(VLOOKUP($D16,'BASE DE DATOS'!$B:$I,5,0),0) -> 0 | J16: =IFERROR(VLOOKUP($D16,'BASE DE DATOS'!$B:$I,6,0),0) -> CL 8 12 10 | K16: =IFERROR(VLOOKUP($D16,'BASE DE DATOS'!$B:$I,7,0),0) -> 3017199935 | L16: =IFERROR(VLOOKUP($D16,'BASE DE DATOS'!$B:$I,8,0),0) -> 0 | M16: 474000 | N16: COSTO
A17: 45722 | B17: 290564067 | D17: =IFERROR(VLOOKUP($E17,'BASE DE DATOS'!$A:$I,2,0)," ") -> 800153993 | E17: ='BASE DE DATOS'!$A$21 -> COMCEL SA | F17: =IFERROR(VLOOKUP($D17,'BASE DE DATOS'!$B:$I,2,0),0) -> NO TIENE | G17: =IFERROR(VLOOKUP($D17,'BASE DE DATOS'!$B:$I,3,0),0) -> NO TIENE | H17: =IFERROR(VLOOKUP($D17,'BASE DE DATOS'!$B:$I,4,0),0) -> NO TIENE | I17: =IFERROR(VLOOKUP($D17,'BASE DE DATOS'!$B:$I,5,0),0) -> NO TIENE | J17: =IFERROR(VLOOKUP($D17,'BASE DE DATOS'!$B:$I,6,0),0) -> 0 | K17: =IFERROR(VLOOKUP($D17,'BASE DE DATOS'!$B:$I,7,0),0) -> 0 | L17: =IFERROR(VLOOKUP($D17,'BASE DE DATOS'!$B:$I,8,0),0) -> 0 | M17: 428999 | N17: GASTO
A18: 45721 | B18: 12 | D18: =IFERROR(VLOOKUP($E18,'BASE DE DATOS'!$A:$I,2,0)," ") -> 14695845 | E18: MERCAFRUVER EL MAYORISTA | F18: =IFERROR(VLOOKUP($D18,'BASE DE DATOS'!$B:$I,2,0),0) -> EDELMIRA | G18: =IFERROR(VLOOKUP($D18,'BASE DE DATOS'!$B:$I,3,0),0) -> 0 | H18: =IFERROR(VLOOKUP($D18,'BASE DE DATOS'!$B:$I,4,0),0) -> MORALES | I18: =IFERROR(VLOOKUP($D18,'BASE DE DATOS'!$B:$I,5,0),0) -> ACOSTA | J18: =IFERROR(VLOOKUP($D18,'BASE DE DATOS'!$B:$I,6,0),0) -> ST 1 MZ 19 VILLAMARINA | K18: =IFERROR(VLOOKUP($D18,'BASE DE DATOS'!$B:$I,7,0),0) -> 3215223609 | L18: =IFERROR(VLOOKUP($D18,'BASE DE DATOS'!$B:$I,8,0),0) -> 0 | M18: 120100 | N18: COSTO
A19: 45721 | B19: 48671 | D19: =IFERROR(VLOOKUP($E19,'BASE DE DATOS'!$A:$I,2,0)," ") -> 9009432434 | E19: ='BASE DE DATOS'!$A$153 -> DOLLARCITY | F19: =IFERROR(VLOOKUP($D19,'BASE DE DATOS'!$B:$I,2,0),0) -> 0 | G19: =IFERROR(VLOOKUP($D19,'BASE DE DATOS'!$B:$I,3,0),0) -> 0 | H19: =IFERROR(VLOOKUP($D19,'BASE DE DATOS'!$B:$I,4,0),0) -> 0 | I19: =IFERROR(VLOOKUP($D19,'BASE DE DATOS'!$B:$I,5,0),0) -> 0 | J19: =IFERROR(VLOOKUP($D19,'BASE DE DATOS'!$B:$I,6,0),0) -> AV 3 57 N 30 | K19: =IFERROR(VLOOKUP($D19,'BASE DE DATOS'!$B:$I,7,0),0) -> 0 | L19: =IFERROR(VLOOKUP($D19,'BASE DE DATOS'!$B:$I,8,0),0) -> 0 | M19: 143500 | N19: GASTO
A20: 45721 | B20: 141992 | D20: =IFERROR(VLOOKUP($E20,'BASE DE DATOS'!$A:$I,2,0)," ") -> 901158397 | E20: ='BASE DE DATOS'!$A$113 -> QUESOS Y QUESOS LA CALIDAD SAS | F20: =IFERROR(VLOOKUP($D20,'BASE DE DATOS'!$B:$I,2,0),0) -> 0 | G20: =IFERROR(VLOOKUP($D20,'BASE DE DATOS'!$B:$I,3,0),0) -> 0 | H20: =IFERROR(VLOOKUP($D20,'BASE DE DATOS'!$B:$I,4,0),0) -> 0 | I20: =IFERROR(VLOOKUP($D20,'BASE DE DATOS'!$B:$I,5,0),0) -> 0 | J20: =IFERROR(VLOOKUP($D20,'BASE DE DATOS'!$B:$I,6,0),0) -> CR 17 33 D 36 | K20: =IFERROR(VLOOKUP($D20,'BASE DE DATOS'!$B:$I,7,0),0) -> 3108368823 | L20: =IFERROR(VLOOKUP($D20,'BASE DE DATOS'!$B:$I,8,0),0) -> 0 | M20: 408000 | N20: COSTO
A21: 45723 | B21: 63279 | D21: =IFERROR(VLOOKUP($E21,'BASE DE DATOS'!$A:$I,2,0)," ") -> 66931449 | E21: ='BASE DE DATOS'!$A$112 -> QUESERA Y SALSAMENTARIA LA MAXIMA | F21: =IFERROR(VLOOKUP($D21,'BASE DE DATOS'!$B:$I,2,0),0) -> NO TIENE | G21: =IFERROR(VLOOKUP($D21,'BASE DE DATOS'!$B:$I,3,0),0) -> NO TIENE | H21: =IFERROR(VLOOKUP($D21,'BASE DE DATOS'!$B:$I,4,0),0) -> NO TIENE | I21: =IFERROR(VLOOKUP($D21,'BASE DE DATOS'!$B:$I,5,0),0) -> NO TIENE | J21: =IFERROR(VLOOKUP($D21,'BASE DE DATOS'!$B:$I,6,0),0) -> CR 12 6 33 | K21: =IFERROR(VLOOKUP($D21,'BASE DE DATOS'!$B:$I,7,0),0) -> 2672346 | L21: =IFERROR(VLOOKUP($D21,'BASE DE DATOS'!$B:$I,8,0),0) -> NO TIENE | M21: 253700 | N21: GASTO
A22: 45722 | B22: 13053 | D22: =IFERROR(VLOOKUP($E22,'BASE DE DATOS'!$A:$I,2,0)," ") -> 66886718 | E22: ='BASE DE DATOS'!$A$107 -> PAPELERIA JUVENIL | F22: =IFERROR(VLOOKUP($D22,'BASE DE DATOS'!$B:$I,2,0),0) -> MARIA | G22: =IFERROR(VLOOKUP($D22,'BASE DE DATOS'!$B:$I,3,0),0) -> ISABEL | H22: =IFERROR(VLOOKUP($D22,'BASE DE DATOS'!$B:$I,4,0),0) -> GIRON | I22: =IFERROR(VLOOKUP($D22,'BASE DE DATOS'!$B:$I,5,0),0) -> CERON | J22: =IFERROR(VLOOKUP($D22,'BASE DE DATOS'!$B:$I,6,0),0) -> CL 6 9 52 | K22: =IFERROR(VLOOKUP($D22,'BASE DE DATOS'!$B:$I,7,0),0) -> 2673706 | L22: =IFERROR(VLOOKUP($D22,'BASE DE DATOS'!$B:$I,8,0),0) -> papeleriajuvenil@gmail.com | M22: 10600 | N22: GASTO
A23: 45723 | B23: 0 | D23: =IFERROR(VLOOKUP($E23,'BASE DE DATOS'!$A:$I,2,0)," ") -> 66931449 | E23: QUESERA Y SALSAMENTARIA LA MAXIMA | F23: =IFERROR(VLOOKUP($D23,'BASE DE DATOS'!$B:$I,2,0),0) -> NO TIENE | G23: =IFERROR(VLOOKUP($D23,'BASE DE DATOS'!$B:$I,3,0),0) -> NO TIENE | H23: =IFERROR(VLOOKUP($D23,'BASE DE DATOS'!$B:$I,4,0),0) -> NO TIENE | I23: =IFERROR(VLOOKUP($D23,'BASE DE DATOS'!$B:$I,5,0),0) -> NO TIENE | J23: =IFERROR(VLOOKUP($D23,'BASE DE DATOS'!$B:$I,6,0),0) -> CR 12 6 33 | K23: =IFERROR(VLOOKUP($D23,'BASE DE DATOS'!$B:$I,7,0),0) -> 2672346 | L23: =IFERROR(VLOOKUP($D23,'BASE DE DATOS'!$B:$I,8,0),0) -> NO TIENE | M23: 55000 | N23: GASTO
A24: 45723 | B24: 13099 | D24: =IFERROR(VLOOKUP($E24,'BASE DE DATOS'!$A:$I,2,0)," ") -> 66886718 | E24: PAPELERIA JUVENIL | F24: =IFERROR(VLOOKUP($D24,'BASE DE DATOS'!$B:$I,2,0),0) -> MARIA | G24: =IFERROR(VLOOKUP($D24,'BASE DE DATOS'!$B:$I,3,0),0) -> ISABEL | H24: =IFERROR(VLOOKUP($D24,'BASE DE DATOS'!$B:$I,4,0),0) -> GIRON | I24: =IFERROR(VLOOKUP($D24,'BASE DE DATOS'!$B:$I,5,0),0) -> CERON | J24: =IFERROR(VLOOKUP($D24,'BASE DE DATOS'!$B:$I,6,0),0) -> CL 6 9 52 | K24: =IFERROR(VLOOKUP($D24,'BASE DE DATOS'!$B:$I,7,0),0) -> 2673706 | L24: =IFERROR(VLOOKUP($D24,'BASE DE DATOS'!$B:$I,8,0),0) -> papeleriajuvenil@gmail.com | M24: 12000 | N24: GASTO
A25: 45722 | B25: 0 | D25: =IFERROR(VLOOKUP($E25,'BASE DE DATOS'!$A:$I,2,0)," ") -> 0 | E25: ='BASE DE DATOS'!$A$8 -> BOLSAS PLASTICAS | F25: =IFERROR(VLOOKUP($D25,'BASE DE DATOS'!$B:$I,2,0),0) -> 0 | G25: =IFERROR(VLOOKUP($D25,'BASE DE DATOS'!$B:$I,3,0),0) -> 0 | H25: =IFERROR(VLOOKUP($D25,'BASE DE DATOS'!$B:$I,4,0),0) -> 0 | I25: =IFERROR(VLOOKUP($D25,'BASE DE DATOS'!$B:$I,5,0),0) -> 0 | J25: =IFERROR(VLOOKUP($D25,'BASE DE DATOS'!$B:$I,6,0),0) -> 0 | K25: =IFERROR(VLOOKUP($D25,'BASE DE DATOS'!$B:$I,7,0),0) -> 0 | L25: =IFERROR(VLOOKUP($D25,'BASE DE DATOS'!$B:$I,8,0),0) -> 0 | M25: 30000 | N25: GASTO
A26: 45722 | B26: 0 | D26: =IFERROR(VLOOKUP($E26,'BASE DE DATOS'!$A:$I,2,0)," ") -> 66929745 | E26: POLLOS EL SABOR | F26: =IFERROR(VLOOKUP($D26,'BASE DE DATOS'!$B:$I,2,0),0) -> MARTHA | G26: =IFERROR(VLOOKUP($D26,'BASE DE DATOS'!$B:$I,3,0),0) -> 0 | H26: =IFERROR(VLOOKUP($D26,'BASE DE DATOS'!$B:$I,4,0),0) -> 0 | I26: =IFERROR(VLOOKUP($D26,'BASE DE DATOS'!$B:$I,5,0),0) -> 0 | J26: =IFERROR(VLOOKUP($D26,'BASE DE DATOS'!$B:$I,6,0),0) -> CL 8 12 10 | K26: =IFERROR(VLOOKUP($D26,'BASE DE DATOS'!$B:$I,7,0),0) -> 3017199935 | L26: =IFERROR(VLOOKUP($D26,'BASE DE DATOS'!$B:$I,8,0),0) -> 0 | M26: 748000 | N26: COSTO
A27: 45723 | B27: 4258 | D27: =IFERROR(VLOOKUP($E27,'BASE DE DATOS'!$A:$I,2,0)," ") -> 66929745 | E27: POLLOS EL SABOR | F27: =IFERROR(VLOOKUP($D27,'BASE DE DATOS'!$B:$I,2,0),0) -> MARTHA | G27: =IFERROR(VLOOKUP($D27,'BASE DE DATOS'!$B:$I,3,0),0) -> 0 | H27: =IFERROR(VLOOKUP($D27,'BASE DE DATOS'!$B:$I,4,0),0) -> 0 | I27: =IFERROR(VLOOKUP($D27,'BASE DE DATOS'!$B:$I,5,0),0) -> 0 | J27: =IFERROR(VLOOKUP($D27,'BASE DE DATOS'!$B:$I,6,0),0) -> CL 8 12 10 | K27: =IFERROR(VLOOKUP($D27,'BASE DE DATOS'!$B:$I,7,0),0) -> 3017199935 | L27: =IFERROR(VLOOKUP($D27,'BASE DE DATOS'!$B:$I,8,0),0) -> 0 | M27: 494550 | N27: COSTO
A28: 45724 | B28: 0 | D28: =IFERROR(VLOOKUP($E28,'BASE DE DATOS'!$A:$I,2,0)," ") -> 66931449 | E28: QUESERA Y SALSAMENTARIA LA MAXIMA | F28: =IFERROR(VLOOKUP($D28,'BASE DE DATOS'!$B:$I,2,0),0) -> NO TIENE | G28: =IFERROR(VLOOKUP($D28,'BASE DE DATOS'!$B:$I,3,0),0) -> NO TIENE | H28: =IFERROR(VLOOKUP($D28,'BASE DE DATOS'!$B:$I,4,0),0) -> NO TIENE | I28: =IFERROR(VLOOKUP($D28,'BASE DE DATOS'!$B:$I,5,0),0) -> NO TIENE | J28: =IFERROR(VLOOKUP($D28,'BASE DE DATOS'!$B:$I,6,0),0) -> CR 12 6 33 | K28: =IFERROR(VLOOKUP($D28,'BASE DE DATOS'!$B:$I,7,0),0) -> 2672346 | L28: =IFERROR(VLOOKUP($D28,'BASE DE DATOS'!$B:$I,8,0),0) -> NO TIENE | M28: 35000 | N28: GASTO
A29: 45724 | B29: 0 | D29: =IFERROR(VLOOKUP($E29,'BASE DE DATOS'!$A:$I,2,0)," ") -> 0 | E29: gastos varios caja/ descuadres | F29: =IFERROR(VLOOKUP($D29,'BASE DE DATOS'!$B:$I,2,0),0) -> 0 | G29: =IFERROR(VLOOKUP($D29,'BASE DE DATOS'!$B:$I,3,0),0) -> 0 | H29: =IFERROR(VLOOKUP($D29,'BASE DE DATOS'!$B:$I,4,0),0) -> 0 | I29: =IFERROR(VLOOKUP($D29,'BASE DE DATOS'!$B:$I,5,0),0) -> 0 | J29: =IFERROR(VLOOKUP($D29,'BASE DE DATOS'!$B:$I,6,0),0) -> 0 | K29: =IFERROR(VLOOKUP($D29,'BASE DE DATOS'!$B:$I,7,0),0) -> 0 | L29: =IFERROR(VLOOKUP($D29,'BASE DE DATOS'!$B:$I,8,0),0) -> 0 | M29: 73000 | N29: GASTO
A30: 45724 | B30: 0 | D30: =IFERROR(VLOOKUP($E30,'BASE DE DATOS'!$A:$I,2,0)," ") -> 0 | E30: gastos varios caja/ descuadres | F30: =IFERROR(VLOOKUP($D30,'BASE DE DATOS'!$B:$I,2,0),0) -> 0 | G30: =IFERROR(VLOOKUP($D30,'BASE DE DATOS'!$B:$I,3,0),0) -> 0 | H30: =IFERROR(VLOOKUP($D30,'BASE DE DATOS'!$B:$I,4,0),0) -> 0 | I30: =IFERROR(VLOOKUP($D30,'BASE DE DATOS'!$B:$I,5,0),0) -> 0 | J30: =IFERROR(VLOOKUP($D30,'BASE DE DATOS'!$B:$I,6,0),0) -> 0 | K30: =IFERROR(VLOOKUP($D30,'BASE DE DATOS'!$B:$I,7,0),0) -> 0 | L30: =IFERROR(VLOOKUP($D30,'BASE DE DATOS'!$B:$I,8,0),0) -> 0 | M30: 147000 | N30: GASTO
A31: 45724 | B31: 5010 | D31: =IFERROR(VLOOKUP($E31,'BASE DE DATOS'!$A:$I,2,0)," ") -> 9017363446 | E31: ='BASE DE DATOS'!$A$141 -> DISTRIBUIDORA ZADAY SAS | F31: =IFERROR(VLOOKUP($D31,'BASE DE DATOS'!$B:$I,2,0),0) -> JORGE | G31: =IFERROR(VLOOKUP($D31,'BASE DE DATOS'!$B:$I,3,0),0) -> 0 | H31: =IFERROR(VLOOKUP($D31,'BASE DE DATOS'!$B:$I,4,0),0) -> MOSQUERA | I31: =IFERROR(VLOOKUP($D31,'BASE DE DATOS'!$B:$I,5,0),0) -> 0 | J31: =IFERROR(VLOOKUP($D31,'BASE DE DATOS'!$B:$I,6,0),0) -> MANZANA T CASA 17 MARIA 2 | K31: =IFERROR(VLOOKUP($D31,'BASE DE DATOS'!$B:$I,7,0),0) -> 3017939209 | L31: =IFERROR(VLOOKUP($D31,'BASE DE DATOS'!$B:$I,8,0),0) -> reporte@seitem.com | M31: 79200 | N31: COSTO
A32: 45723 | B32: 697105 | D32: =IFERROR(VLOOKUP($E32,'BASE DE DATOS'!$A:$I,2,0)," ") -> 890500726 | E32: ='BASE DE DATOS'!$A$102 -> NORTESANTANDEREANA DE GAS SA ESP | F32: =IFERROR(VLOOKUP($D32,'BASE DE DATOS'!$B:$I,2,0),0) -> NO TIENE | G32: =IFERROR(VLOOKUP($D32,'BASE DE DATOS'!$B:$I,3,0),0) -> NO TIENE | H32: =IFERROR(VLOOKUP($D32,'BASE DE DATOS'!$B:$I,4,0),0) -> NO TIENE | I32: =IFERROR(VLOOKUP($D32,'BASE DE DATOS'!$B:$I,5,0),0) -> NO TIENE | J32: =IFERROR(VLOOKUP($D32,'BASE DE DATOS'!$B:$I,6,0),0) -> 0 | K32: =IFERROR(VLOOKUP($D32,'BASE DE DATOS'!$B:$I,7,0),0) -> 3208899901 | L32: =IFERROR(VLOOKUP($D32,'BASE DE DATOS'!$B:$I,8,0),0) -> 0 | M32: 420000 | N32: SERVICIOS
A33: 45724 | B33: 0 | D33: =IFERROR(VLOOKUP($E33,'BASE DE DATOS'!$A:$I,2,0)," ") -> 901473419 | E33: ='BASE DE DATOS'!$A$40 -> DISTRIBUCIONES JACOTA ZOMAC SAS | F33: =IFERROR(VLOOKUP($D33,'BASE DE DATOS'!$B:$I,2,0),0) -> 0 | G33: =IFERROR(VLOOKUP($D33,'BASE DE DATOS'!$B:$I,3,0),0) -> 0 | H33: =IFERROR(VLOOKUP($D33,'BASE DE DATOS'!$B:$I,4,0),0) -> 0 | I33: =IFERROR(VLOOKUP($D33,'BASE DE DATOS'!$B:$I,5,0),0) -> 0 | J33: =IFERROR(VLOOKUP($D33,'BASE DE DATOS'!$B:$I,6,0),0) -> CR 10 5 32 | K33: =IFERROR(VLOOKUP($D33,'BASE DE DATOS'!$B:$I,7,0),0) -> 3147560646 | L33: =IFERROR(VLOOKUP($D33,'BASE DE DATOS'!$B:$I,8,0),0) -> jacota.distribuciones@outlook.com | M33: 501900 | N33: COSTO
A34: 45717 | B34: 6170 | D34: =IFERROR(VLOOKUP($E34,'BASE DE DATOS'!$A:$I,2,0)," ") -> 66660257 | E34: ='BASE DE DATOS'!$A$38 -> DISOIL | F34: =IFERROR(VLOOKUP($D34,'BASE DE DATOS'!$B:$I,2,0),0) -> 0 | G34: =IFERROR(VLOOKUP($D34,'BASE DE DATOS'!$B:$I,3,0),0) -> 0 | H34: =IFERROR(VLOOKUP($D34,'BASE DE DATOS'!$B:$I,4,0),0) -> 0 | I34: =IFERROR(VLOOKUP($D34,'BASE DE DATOS'!$B:$I,5,0),0) -> 0 | J34: =IFERROR(VLOOKUP($D34,'BASE DE DATOS'!$B:$I,6,0),0) -> CL 21 31 37 | K34: =IFERROR(VLOOKUP($D34,'BASE DE DATOS'!$B:$I,7,0),0) -> 3005547057 | L34: =IFERROR(VLOOKUP($D34,'BASE DE DATOS'!$B:$I,8,0),0) -> 0 | M34: 292000 | N34: SERVICIOS
A35: 45724 | B35: 6219 | D35: =IFERROR(VLOOKUP($E35,'BASE DE DATOS'!$A:$I,2,0)," ") -> 66660257 | E35: DISOIL | F35: =IFERROR(VLOOKUP($D35,'BASE DE DATOS'!$B:$I,2,0),0) -> 0 | G35: =IFERROR(VLOOKUP($D35,'BASE DE DATOS'!$B:$I,3,0),0) -> 0 | H35: =IFERROR(VLOOKUP($D35,'BASE DE DATOS'!$B:$I,4,0),0) -> 0 | I35: =IFERROR(VLOOKUP($D35,'BASE DE DATOS'!$B:$I,5,0),0) -> 0 | J35: =IFERROR(VLOOKUP($D35,'BASE DE DATOS'!$B:$I,6,0),0) -> CL 21 31 37 | K35: =IFERROR(VLOOKUP($D35,'BASE DE DATOS'!$B:$I,7,0),0) -> 3005547057 | L35: =IFERROR(VLOOKUP($D35,'BASE DE DATOS'!$B:$I,8,0),0) -> 0 | M35: 292000 | N35: SERVICIOS
A36: 45725 | B36: 462469 | D36: =IFERROR(VLOOKUP($E36,'BASE DE DATOS'!$A:$I,2,0)," ") -> 815002459 | E36: ='BASE DE DATOS'!$A$94 -> MERCAPAVA SA | F36: =IFERROR(VLOOKUP($D36,'BASE DE DATOS'!$B:$I,2,0),0) -> NO TIENE | G36: =IFERROR(VLOOKUP($D36,'BASE DE DATOS'!$B:$I,3,0),0) -> NO TIENE | H36: =IFERROR(VLOOKUP($D36,'BASE DE DATOS'!$B:$I,4,0),0) -> NO TIENE | I36: =IFERROR(VLOOKUP($D36,'BASE DE DATOS'!$B:$I,5,0),0) -> NO TIENE | J36: =IFERROR(VLOOKUP($D36,'BASE DE DATOS'!$B:$I,6,0),0) -> CL 7 12 03 | K36: =IFERROR(VLOOKUP($D36,'BASE DE DATOS'!$B:$I,7,0),0) -> 3136831049 | L36: =IFERROR(VLOOKUP($D36,'BASE DE DATOS'!$B:$I,8,0),0) -> 0 | M36: 36820 | N36: GASTO
A37: 45725 | B37: 84 | D37: =IFERROR(VLOOKUP($E37,'BASE DE DATOS'!$A:$I,2,0)," ") -> 1112230545 | E37: ='BASE DE DATOS'!$A$115 -> salsamentaria | F37: =IFERROR(VLOOKUP($D37,'BASE DE DATOS'!$B:$I,2,0),0) -> 0 | G37: =IFERROR(VLOOKUP($D37,'BASE DE DATOS'!$B:$I,3,0),0) -> 0 | H37: =IFERROR(VLOOKUP($D37,'BASE DE DATOS'!$B:$I,4,0),0) -> 0 | I37: =IFERROR(VLOOKUP($D37,'BASE DE DATOS'!$B:$I,5,0),0) -> 0 | J37: =IFERROR(VLOOKUP($D37,'BASE DE DATOS'!$B:$I,6,0),0) -> 0 | K37: =IFERROR(VLOOKUP($D37,'BASE DE DATOS'!$B:$I,7,0),0) -> 3107292255 | L37: =IFERROR(VLOOKUP($D37,'BASE DE DATOS'!$B:$I,8,0),0) -> NO TIENE | M37: 42800 | N37: GASTO
A38: 45725 | B38: 0 | D38: =IFERROR(VLOOKUP($E38,'BASE DE DATOS'!$A:$I,2,0)," ") -> 0 | E38: =$E$10 -> MERCAFRUVER LA ECONOMIA demi pradera | F38: =IFERROR(VLOOKUP($D38,'BASE DE DATOS'!$B:$I,2,0),0) -> 0 | G38: =IFERROR(VLOOKUP($D38,'BASE DE DATOS'!$B:$I,3,0),0) -> 0 | H38: =IFERROR(VLOOKUP($D38,'BASE DE DATOS'!$B:$I,4,0),0) -> 0 | I38: =IFERROR(VLOOKUP($D38,'BASE DE DATOS'!$B:$I,5,0),0) -> 0 | J38: =IFERROR(VLOOKUP($D38,'BASE DE DATOS'!$B:$I,6,0),0) -> 0 | K38: =IFERROR(VLOOKUP($D38,'BASE DE DATOS'!$B:$I,7,0),0) -> 0 | L38: =IFERROR(VLOOKUP($D38,'BASE DE DATOS'!$B:$I,8,0),0) -> 0 | M38: 168000 | N38: COSTO
A39: 45724 | B39: 0 | D39: =IFERROR(VLOOKUP($E39,'BASE DE DATOS'!$A:$I,2,0)," ") -> 0 | E39: gastos varios caja/ descuadres | F39: =IFERROR(VLOOKUP($D39,'BASE DE DATOS'!$B:$I,2,0),0) -> 0 | G39: =IFERROR(VLOOKUP($D39,'BASE DE DATOS'!$B:$I,3,0),0) -> 0 | H39: =IFERROR(VLOOKUP($D39,'BASE DE DATOS'!$B:$I,4,0),0) -> 0 | I39: =IFERROR(VLOOKUP($D39,'BASE DE DATOS'!$B:$I,5,0),0) -> 0 | J39: =IFERROR(VLOOKUP($D39,'BASE DE DATOS'!$B:$I,6,0),0) -> 0 | K39: =IFERROR(VLOOKUP($D39,'BASE DE DATOS'!$B:$I,7,0),0) -> 0 | L39: =IFERROR(VLOOKUP($D39,'BASE DE DATOS'!$B:$I,8,0),0) -> 0 | M39: 97000 | N39: GASTO
A40: 45724 | B40: 0 | D40: =IFERROR(VLOOKUP($E40,'BASE DE DATOS'!$A:$I,2,0)," ") -> 0 | E40: ='BASE DE DATOS'!$A$174 -> LECHUGA | F40: =IFERROR(VLOOKUP($D40,'BASE DE DATOS'!$B:$I,2,0),0) -> 0 | G40: =IFERROR(VLOOKUP($D40,'BASE DE DATOS'!$B:$I,3,0),0) -> 0 | H40: =IFERROR(VLOOKUP($D40,'BASE DE DATOS'!$B:$I,4,0),0) -> 0 | I40: =IFERROR(VLOOKUP($D40,'BASE DE DATOS'!$B:$I,5,0),0) -> 0 | J40: =IFERROR(VLOOKUP($D40,'BASE DE DATOS'!$B:$I,6,0),0) -> 0 | K40: =IFERROR(VLOOKUP($D40,'BASE DE DATOS'!$B:$I,7,0),0) -> 0 | L40: =IFERROR(VLOOKUP($D40,'BASE DE DATOS'!$B:$I,8,0),0) -> 0 | M40: 15400 | N40: COSTO
A41: 45725 | B41: 0 | D41: =IFERROR(VLOOKUP($E41,'BASE DE DATOS'!$A:$I,2,0)," ") -> 1112230545 | E41: salsamentaria | F41: =IFERROR(VLOOKUP($D41,'BASE DE DATOS'!$B:$I,2,0),0) -> 0 | G41: =IFERROR(VLOOKUP($D41,'BASE DE DATOS'!$B:$I,3,0),0) -> 0 | H41: =IFERROR(VLOOKUP($D41,'BASE DE DATOS'!$B:$I,4,0),0) -> 0 | I41: =IFERROR(VLOOKUP($D41,'BASE DE DATOS'!$B:$I,5,0),0) -> 0 | J41: =IFERROR(VLOOKUP($D41,'BASE DE DATOS'!$B:$I,6,0),0) -> 0 | K41: =IFERROR(VLOOKUP($D41,'BASE DE DATOS'!$B:$I,7,0),0) -> 3107292255 | L41: =IFERROR(VLOOKUP($D41,'BASE DE DATOS'!$B:$I,8,0),0) -> NO TIENE | M41: 130000 | N41: GASTO
A42: 45724 | B42: 159 | D42: =IFERROR(VLOOKUP($E42,'BASE DE DATOS'!$A:$I,2,0)," ") -> 1112230545 | E42: salsamentaria | F42: =IFERROR(VLOOKUP($D42,'BASE DE DATOS'!$B:$I,2,0),0) -> 0 | G42: =IFERROR(VLOOKUP($D42,'BASE DE DATOS'!$B:$I,3,0),0) -> 0 | H42: =IFERROR(VLOOKUP($D42,'BASE DE DATOS'!$B:$I,4,0),0) -> 0 | I42: =IFERROR(VLOOKUP($D42,'BASE DE DATOS'!$B:$I,5,0),0) -> 0 | J42: =IFERROR(VLOOKUP($D42,'BASE DE DATOS'!$B:$I,6,0),0) -> 0 | K42: =IFERROR(VLOOKUP($D42,'BASE DE DATOS'!$B:$I,7,0),0) -> 3107292255 | L42: =IFERROR(VLOOKUP($D42,'BASE DE DATOS'!$B:$I,8,0),0) -> NO TIENE | M42: 26000 | N42: GASTO
A43: 45724 | B43: 0 | D43: =IFERROR(VLOOKUP($E43,'BASE DE DATOS'!$A:$I,2,0)," ") -> 1112230545 | E43: salsamentaria | F43: =IFERROR(VLOOKUP($D43,'BASE DE DATOS'!$B:$I,2,0),0) -> 0 | G43: =IFERROR(VLOOKUP($D43,'BASE DE DATOS'!$B:$I,3,0),0) -> 0 | H43: =IFERROR(VLOOKUP($D43,'BASE DE DATOS'!$B:$I,4,0),0) -> 0 | I43: =IFERROR(VLOOKUP($D43,'BASE DE DATOS'!$B:$I,5,0),0) -> 0 | J43: =IFERROR(VLOOKUP($D43,'BASE DE DATOS'!$B:$I,6,0),0) -> 0 | K43: =IFERROR(VLOOKUP($D43,'BASE DE DATOS'!$B:$I,7,0),0) -> 3107292255 | L43: =IFERROR(VLOOKUP($D43,'BASE DE DATOS'!$B:$I,8,0),0) -> NO TIENE | M43: 176000 | N43: COSTO
A44: 45724 | B44: 4359 | D44: =IFERROR(VLOOKUP($E44,'BASE DE DATOS'!$A:$I,2,0)," ") -> 66929745 | E44: POLLOS EL SABOR | F44: =IFERROR(VLOOKUP($D44,'BASE DE DATOS'!$B:$I,2,0),0) -> MARTHA | G44: =IFERROR(VLOOKUP($D44,'BASE DE DATOS'!$B:$I,3,0),0) -> 0 | H44: =IFERROR(VLOOKUP($D44,'BASE DE DATOS'!$B:$I,4,0),0) -> 0 | I44: =IFERROR(VLOOKUP($D44,'BASE DE DATOS'!$B:$I,5,0),0) -> 0 | J44: =IFERROR(VLOOKUP($D44,'BASE DE DATOS'!$B:$I,6,0),0) -> CL 8 12 10 | K44: =IFERROR(VLOOKUP($D44,'BASE DE DATOS'!$B:$I,7,0),0) -> 3017199935 | L44: =IFERROR(VLOOKUP($D44,'BASE DE DATOS'!$B:$I,8,0),0) -> 0 | M44: 477200 | N44: COSTO
A45: 45724 | B45: 7000328 | D45: =IFERROR(VLOOKUP($E45,'BASE DE DATOS'!$A:$I,2,0)," ") -> 8150048801 | E45: ='BASE DE DATOS'!$A$143 -> DISTRIBUIDORA TIENDAS Y MARCAS | F45: =IFERROR(VLOOKUP($D45,'BASE DE DATOS'!$B:$I,2,0),0) -> ELIANA | G45: =IFERROR(VLOOKUP($D45,'BASE DE DATOS'!$B:$I,3,0),0) -> MARIA | H45: =IFERROR(VLOOKUP($D45,'BASE DE DATOS'!$B:$I,4,0),0) -> 0 | I45: =IFERROR(VLOOKUP($D45,'BASE DE DATOS'!$B:$I,5,0),0) -> 0 | J45: =IFERROR(VLOOKUP($D45,'BASE DE DATOS'!$B:$I,6,0),0) -> CRA 34 31 35 BOD 2 PALMIRA | K45: =IFERROR(VLOOKUP($D45,'BASE DE DATOS'!$B:$I,7,0),0) -> 3228469553 | L45: =IFERROR(VLOOKUP($D45,'BASE DE DATOS'!$B:$I,8,0),0) -> 0 | M45: 186851 | N45: COSTO
A46: 45726 | B46: 6 | D46: =IFERROR(VLOOKUP($E46,'BASE DE DATOS'!$A:$I,2,0)," ") -> 29530093 | E46: =[1]FEBRERO!E75 -> YUGLAXI YOXIELI RENGIFO BARBOZA | F46: =IFERROR(VLOOKUP($D46,'BASE DE DATOS'!$B:$I,2,0),0) -> YUGLAXI | G46: =IFERROR(VLOOKUP($D46,'BASE DE DATOS'!$B:$I,3,0),0) -> YOXIELI | H46: =IFERROR(VLOOKUP($D46,'BASE DE DATOS'!$B:$I,4,0),0) -> RENGIFO | I46: =IFERROR(VLOOKUP($D46,'BASE DE DATOS'!$B:$I,5,0),0) -> BARBOZA | J46: =IFERROR(VLOOKUP($D46,'BASE DE DATOS'!$B:$I,6,0),0) -> CARR 15 MAZ C CASA 28 LAS MARGARITAS | K46: =IFERROR(VLOOKUP($D46,'BASE DE DATOS'!$B:$I,7,0),0) -> 3217261359 | L46: =IFERROR(VLOOKUP($D46,'BASE DE DATOS'!$B:$I,8,0),0) -> 0 | M46: 437000 | N46: EMPLEADO
A47: =$A$46 -> 45726 | B47: 15 | D47: =IFERROR(VLOOKUP($E47,'BASE DE DATOS'!$A:$I,2,0)," ") -> 1114311126 | E47: =[1]FEBRERO!E76 -> CRISTIAN CAMILO PORTILLO LOAIZA | F47: =IFERROR(VLOOKUP($D47,'BASE DE DATOS'!$B:$I,2,0),0) -> CRISTIAN | G47: =IFERROR(VLOOKUP($D47,'BASE DE DATOS'!$B:$I,3,0),0) -> CAMILO | H47: =IFERROR(VLOOKUP($D47,'BASE DE DATOS'!$B:$I,4,0),0) -> PORTILLO | I47: =IFERROR(VLOOKUP($D47,'BASE DE DATOS'!$B:$I,5,0),0) -> LOAIZA | J47: =IFERROR(VLOOKUP($D47,'BASE DE DATOS'!$B:$I,6,0),0) -> CR 17# 10-27 B- COMUNEROS | K47: =IFERROR(VLOOKUP($D47,'BASE DE DATOS'!$B:$I,7,0),0) -> 3126574517 | L47: =IFERROR(VLOOKUP($D47,'BASE DE DATOS'!$B:$I,8,0),0) -> 0 | M47: 470000 | N47: =$N$46 -> EMPLEADO
A48: =$A$46 -> 45726 | B48: 9 | D48: =IFERROR(VLOOKUP($E48,'BASE DE DATOS'!$A:$I,2,0)," ") -> 1114623352 | E48: =[1]FEBRERO!E77 -> JUAN MANUEL CORREA ORTIZ | F48: =IFERROR(VLOOKUP($D48,'BASE DE DATOS'!$B:$I,2,0),0) -> JUAN | G48: =IFERROR(VLOOKUP($D48,'BASE DE DATOS'!$B:$I,3,0),0) -> MANUEL | H48: =IFERROR(VLOOKUP($D48,'BASE DE DATOS'!$B:$I,4,0),0) -> CORREA | I48: =IFERROR(VLOOKUP($D48,'BASE DE DATOS'!$B:$I,5,0),0) -> ORTIZ | J48: =IFERROR(VLOOKUP($D48,'BASE DE DATOS'!$B:$I,6,0),0) -> CALLE 8 7-57 | K48: =IFERROR(VLOOKUP($D48,'BASE DE DATOS'!$B:$I,7,0),0) -> 3182626617 | L48: =IFERROR(VLOOKUP($D48,'BASE DE DATOS'!$B:$I,8,0),0) -> 0 | M48: 282000 | N48: =N52 -> EMPLEADO
A49: =$A$46 -> 45726 | B49: 15 | D49: =IFERROR(VLOOKUP($E49,'BASE DE DATOS'!$A:$I,2,0)," ") -> 18652153 | E49: =[1]FEBRERO!E78 -> YANCARLYS RODRIGUEZ | F49: =IFERROR(VLOOKUP($D49,'BASE DE DATOS'!$B:$I,2,0),0) -> YANCARLYS | G49: =IFERROR(VLOOKUP($D49,'BASE DE DATOS'!$B:$I,3,0),0) -> JOSELIN | H49: =IFERROR(VLOOKUP($D49,'BASE DE DATOS'!$B:$I,4,0),0) -> RODRIGUEZ | I49: =IFERROR(VLOOKUP($D49,'BASE DE DATOS'!$B:$I,5,0),0) -> GUEVARA | J49: =IFERROR(VLOOKUP($D49,'BASE DE DATOS'!$B:$I,6,0),0) -> PRADOS DE LA COLINA MN H CASA 1 | K49: =IFERROR(VLOOKUP($D49,'BASE DE DATOS'!$B:$I,7,0),0) -> 3249778826 | L49: =IFERROR(VLOOKUP($D49,'BASE DE DATOS'!$B:$I,8,0),0) -> 0 | M49: 172000 | N49: =$N$46 -> EMPLEADO
A50: =$A$46 -> 45726 | B50: 71 | D50: =IFERROR(VLOOKUP($E50,'BASE DE DATOS'!$A:$I,2,0)," ") -> 1007616371 | E50: =[1]FEBRERO!E79 -> LEIDY KARINA HURTADO | F50: =IFERROR(VLOOKUP($D50,'BASE DE DATOS'!$B:$I,2,0),0) -> LEIDY | G50: =IFERROR(VLOOKUP($D50,'BASE DE DATOS'!$B:$I,3,0),0) -> KARINA | H50: =IFERROR(VLOOKUP($D50,'BASE DE DATOS'!$B:$I,4,0),0) -> HURTADO | I50: =IFERROR(VLOOKUP($D50,'BASE DE DATOS'!$B:$I,5,0),0) -> 0 | J50: =IFERROR(VLOOKUP($D50,'BASE DE DATOS'!$B:$I,6,0),0) -> CR 10 1A 57 | K50: =IFERROR(VLOOKUP($D50,'BASE DE DATOS'!$B:$I,7,0),0) -> 3168609680 | L50: =IFERROR(VLOOKUP($D50,'BASE DE DATOS'!$B:$I,8,0),0) -> 0 | M50: 600000 | N50: =$N$46 -> EMPLEADO
A51: =$A$46 -> 45726 | B51: 2 | D51: =IFERROR(VLOOKUP($E51,'BASE DE DATOS'!$A:$I,2,0)," ") -> 1090096266 | E51: =[1]FEBRERO!E80 -> ISABELA TANGARIFE MARULANDA | F51: =IFERROR(VLOOKUP($D51,'BASE DE DATOS'!$B:$I,2,0),0) -> ISABELA | G51: =IFERROR(VLOOKUP($D51,'BASE DE DATOS'!$B:$I,3,0),0) -> 0 | H51: =IFERROR(VLOOKUP($D51,'BASE DE DATOS'!$B:$I,4,0),0) -> TANGARIFE | I51: =IFERROR(VLOOKUP($D51,'BASE DE DATOS'!$B:$I,5,0),0) -> MARULANDA | J51: =IFERROR(VLOOKUP($D51,'BASE DE DATOS'!$B:$I,6,0),0) -> CALLE 8 9-49 JORGE ELIECER | K51: =IFERROR(VLOOKUP($D51,'BASE DE DATOS'!$B:$I,7,0),0) -> 3155015204 | L51: =IFERROR(VLOOKUP($D51,'BASE DE DATOS'!$B:$I,8,0),0) -> 0 | M51: 301000 | N51: =$N$46 -> EMPLEADO
A52: =$A$46 -> 45726 | B52: 0 | D52: =IFERROR(VLOOKUP($E52,'BASE DE DATOS'!$A:$I,2,0)," ") -> 1114623744 | E52: =[1]FEBRERO!E81 -> REIMON DAVID PIMIENTO CARDENAS | F52: =IFERROR(VLOOKUP($D52,'BASE DE DATOS'!$B:$I,2,0),0) -> REIMON | G52: =IFERROR(VLOOKUP($D52,'BASE DE DATOS'!$B:$I,3,0),0) -> DAVID | H52: =IFERROR(VLOOKUP($D52,'BASE DE DATOS'!$B:$I,4,0),0) -> PIMIENTO | I52: =IFERROR(VLOOKUP($D52,'BASE DE DATOS'!$B:$I,5,0),0) -> CARDENAS | J52: =IFERROR(VLOOKUP($D52,'BASE DE DATOS'!$B:$I,6,0),0) -> 0 | K52: =IFERROR(VLOOKUP($D52,'BASE DE DATOS'!$B:$I,7,0),0) -> 0 | L52: =IFERROR(VLOOKUP($D52,'BASE DE DATOS'!$B:$I,8,0),0) -> 0 | M52: 94000 | N52: =$N$46 -> EMPLEADO
A53: =$A$46 -> 45726 | B53: 49 | D53: =IFERROR(VLOOKUP($E53,'BASE DE DATOS'!$A:$I,2,0)," ") -> 1114621431 | E53: =[1]FEBRERO!E82 -> DANNA SOALRTE ROJAS | F53: =IFERROR(VLOOKUP($D53,'BASE DE DATOS'!$B:$I,2,0),0) -> DANNA | G53: =IFERROR(VLOOKUP($D53,'BASE DE DATOS'!$B:$I,3,0),0) -> 0 | H53: =IFERROR(VLOOKUP($D53,'BASE DE DATOS'!$B:$I,4,0),0) -> SOALRTE | I53: =IFERROR(VLOOKUP($D53,'BASE DE DATOS'!$B:$I,5,0),0) -> ROJAS | J53: =IFERROR(VLOOKUP($D53,'BASE DE DATOS'!$B:$I,6,0),0) -> CR 3 5 38 | K53: =IFERROR(VLOOKUP($D53,'BASE DE DATOS'!$B:$I,7,0),0) -> 3027634803 | L53: =IFERROR(VLOOKUP($D53,'BASE DE DATOS'!$B:$I,8,0),0) -> 0 | M53: 600000 | N53: =$N$46 -> EMPLEADO
A54: =$A$46 -> 45726 | B54: 48 | D54: =IFERROR(VLOOKUP($E54,'BASE DE DATOS'!$A:$I,2,0)," ") -> 1006352061 | E54: =[1]FEBRERO!E83 -> HERNAN DARIO VARGAS NUÑEZ | F54: =IFERROR(VLOOKUP($D54,'BASE DE DATOS'!$B:$I,2,0),0) -> HERNAN | G54: =IFERROR(VLOOKUP($D54,'BASE DE DATOS'!$B:$I,3,0),0) -> DARIO | H54: =IFERROR(VLOOKUP($D54,'BASE DE DATOS'!$B:$I,4,0),0) -> VARGAS | I54: =IFERROR(VLOOKUP($D54,'BASE DE DATOS'!$B:$I,5,0),0) -> NUÑEZ | J54: =IFERROR(VLOOKUP($D54,'BASE DE DATOS'!$B:$I,6,0),0) -> CL 8 2 85 | K54: =IFERROR(VLOOKUP($D54,'BASE DE DATOS'!$B:$I,7,0),0) -> 3127898693 | L54: =IFERROR(VLOOKUP($D54,'BASE DE DATOS'!$B:$I,8,0),0) -> 0 | M54: 387000 | N54: =$N$46 -> EMPLEADO
A55: 45733 | B55: 9482542153 | D55: =IFERROR(VLOOKUP($E55,'BASE DE DATOS'!$A:$I,2,0)," ") -> 900147238 | E55: ='BASE DE DATOS'!$A$5 -> APORTES EN LINEA | F55: =IFERROR(VLOOKUP($D55,'BASE DE DATOS'!$B:$I,2,0),0) -> 0 | G55: =IFERROR(VLOOKUP($D55,'BASE DE DATOS'!$B:$I,3,0),0) -> 0 | H55: =IFERROR(VLOOKUP($D55,'BASE DE DATOS'!$B:$I,4,0),0) -> 0 | I55: =IFERROR(VLOOKUP($D55,'BASE DE DATOS'!$B:$I,5,0),0) -> 0 | J55: =IFERROR(VLOOKUP($D55,'BASE DE DATOS'!$B:$I,6,0),0) -> CR 14ª No. 101-47 | K55: =IFERROR(VLOOKUP($D55,'BASE DE DATOS'!$B:$I,7,0),0) -> 4853939 | L55: =IFERROR(VLOOKUP($D55,'BASE DE DATOS'!$B:$I,8,0),0) -> 0 | M55: 440500 | N55: COSTO
A56: 45733 | B56: 9482503642 | D56: =IFERROR(VLOOKUP($E56,'BASE DE DATOS'!$A:$I,2,0)," ") -> 900147238 | E56: APORTES EN LINEA | F56: =IFERROR(VLOOKUP($D56,'BASE DE DATOS'!$B:$I,2,0),0) -> 0 | G56: =IFERROR(VLOOKUP($D56,'BASE DE DATOS'!$B:$I,3,0),0) -> 0 | H56: =IFERROR(VLOOKUP($D56,'BASE DE DATOS'!$B:$I,4,0),0) -> 0 | I56: =IFERROR(VLOOKUP($D56,'BASE DE DATOS'!$B:$I,5,0),0) -> 0 | J56: =IFERROR(VLOOKUP($D56,'BASE DE DATOS'!$B:$I,6,0),0) -> CR 14ª No. 101-47 | K56: =IFERROR(VLOOKUP($D56,'BASE DE DATOS'!$B:$I,7,0),0) -> 4853939 | L56: =IFERROR(VLOOKUP($D56,'BASE DE DATOS'!$B:$I,8,0),0) -> 0 | M56: 467800 | N56: COSTO
A57: 45731 | B57: 6299 | D57: =IFERROR(VLOOKUP($E57,'BASE DE DATOS'!$A:$I,2,0)," ") -> 66660257 | E57: DISOIL | F57: =IFERROR(VLOOKUP($D57,'BASE DE DATOS'!$B:$I,2,0),0) -> 0 | G57: =IFERROR(VLOOKUP($D57,'BASE DE DATOS'!$B:$I,3,0),0) -> 0 | H57: =IFERROR(VLOOKUP($D57,'BASE DE DATOS'!$B:$I,4,0),0) -> 0 | I57: =IFERROR(VLOOKUP($D57,'BASE DE DATOS'!$B:$I,5,0),0) -> 0 | J57: =IFERROR(VLOOKUP($D57,'BASE DE DATOS'!$B:$I,6,0),0) -> CL 21 31 37 | K57: =IFERROR(VLOOKUP($D57,'BASE DE DATOS'!$B:$I,7,0),0) -> 3005547057 | L57: =IFERROR(VLOOKUP($D57,'BASE DE DATOS'!$B:$I,8,0),0) -> 0 | M57: 292000 | N57: SERVICIOS
A58: 45728 | B58: 142198 | D58: =IFERROR(VLOOKUP($E58,'BASE DE DATOS'!$A:$I,2,0)," ") -> 901158397 | E58: QUESOS Y QUESOS LA CALIDAD SAS | F58: =IFERROR(VLOOKUP($D58,'BASE DE DATOS'!$B:$I,2,0),0) -> 0 | G58: =IFERROR(VLOOKUP($D58,'BASE DE DATOS'!$B:$I,3,0),0) -> 0 | H58: =IFERROR(VLOOKUP($D58,'BASE DE DATOS'!$B:$I,4,0),0) -> 0 | I58: =IFERROR(VLOOKUP($D58,'BASE DE DATOS'!$B:$I,5,0),0) -> 0 | J58: =IFERROR(VLOOKUP($D58,'BASE DE DATOS'!$B:$I,6,0),0) -> CR 17 33 D 36 | K58: =IFERROR(VLOOKUP($D58,'BASE DE DATOS'!$B:$I,7,0),0) -> 3108368823 | L58: =IFERROR(VLOOKUP($D58,'BASE DE DATOS'!$B:$I,8,0),0) -> 0 | M58: 714000 | N58: COSTO
A59: 45731 | B59: 30 | D59: =IFERROR(VLOOKUP($E59,'BASE DE DATOS'!$A:$I,2,0)," ") -> 1006218066 | E59: ='BASE DE DATOS'!$A$29 -> CRISTIAN YAHIR GUERRERO GIRON | F59: =IFERROR(VLOOKUP($D59,'BASE DE DATOS'!$B:$I,2,0),0) -> CRISTIAN | G59: =IFERROR(VLOOKUP($D59,'BASE DE DATOS'!$B:$I,3,0),0) -> YAHIR | H59: =IFERROR(VLOOKUP($D59,'BASE DE DATOS'!$B:$I,4,0),0) -> GUERRERO | I59: =IFERROR(VLOOKUP($D59,'BASE DE DATOS'!$B:$I,5,0),0) -> GIRON | J59: =IFERROR(VLOOKUP($D59,'BASE DE DATOS'!$B:$I,6,0),0) -> CL 10 14 63 | K59: =IFERROR(VLOOKUP($D59,'BASE DE DATOS'!$B:$I,7,0),0) -> 3215272745 | L59: =IFERROR(VLOOKUP($D59,'BASE DE DATOS'!$B:$I,8,0),0) -> 0 | M59: 1024800 | N59: EMPLEADO GOTA
A60: 45731 | B60: 11 | D60: =IFERROR(VLOOKUP($E60,'BASE DE DATOS'!$A:$I,2,0)," ") -> 1006216897 | E60: ='BASE DE DATOS'!$A$164 -> JOSE MANUEL OCAMPO VILLADA | F60: =IFERROR(VLOOKUP($D60,'BASE DE DATOS'!$B:$I,2,0),0) -> JOSE | G60: =IFERROR(VLOOKUP($D60,'BASE DE DATOS'!$B:$I,3,0),0) -> MANUEL | H60: =IFERROR(VLOOKUP($D60,'BASE DE DATOS'!$B:$I,4,0),0) -> OCAMPO | I60: =IFERROR(VLOOKUP($D60,'BASE DE DATOS'!$B:$I,5,0),0) -> VILLADA | J60: =IFERROR(VLOOKUP($D60,'BASE DE DATOS'!$B:$I,6,0),0) -> MZN H CASA 7 P/MAYO | K60: =IFERROR(VLOOKUP($D60,'BASE DE DATOS'!$B:$I,7,0),0) -> 3148828370 | L60: =IFERROR(VLOOKUP($D60,'BASE DE DATOS'!$B:$I,8,0),0) -> 0 | M60: 1174384 | N60: EMPLEADO GOTA
A61: 45727 | B61: 0 | D61: =IFERROR(VLOOKUP($E61,'BASE DE DATOS'!$A:$I,2,0)," ") -> 0 | E61: aguacates | F61: =IFERROR(VLOOKUP($D61,'BASE DE DATOS'!$B:$I,2,0),0) -> 0 | G61: =IFERROR(VLOOKUP($D61,'BASE DE DATOS'!$B:$I,3,0),0) -> 0 | H61: =IFERROR(VLOOKUP($D61,'BASE DE DATOS'!$B:$I,4,0),0) -> 0 | I61: =IFERROR(VLOOKUP($D61,'BASE DE DATOS'!$B:$I,5,0),0) -> 0 | J61: =IFERROR(VLOOKUP($D61,'BASE DE DATOS'!$B:$I,6,0),0) -> 0 | K61: =IFERROR(VLOOKUP($D61,'BASE DE DATOS'!$B:$I,7,0),0) -> 0 | L61: =IFERROR(VLOOKUP($D61,'BASE DE DATOS'!$B:$I,8,0),0) -> 0 | M61: 250000 | N61: COSTO
A62: 45728 | B62: 4652 | D62: =IFERROR(VLOOKUP($E62,'BASE DE DATOS'!$A:$I,2,0)," ") -> 66929745 | E62: POLLOS EL SABOR | F62: =IFERROR(VLOOKUP($D62,'BASE DE DATOS'!$B:$I,2,0),0) -> MARTHA | G62: =IFERROR(VLOOKUP($D62,'BASE DE DATOS'!$B:$I,3,0),0) -> 0 | H62: =IFERROR(VLOOKUP($D62,'BASE DE DATOS'!$B:$I,4,0),0) -> 0 | I62: =IFERROR(VLOOKUP($D62,'BASE DE DATOS'!$B:$I,5,0),0) -> 0 | J62: =IFERROR(VLOOKUP($D62,'BASE DE DATOS'!$B:$I,6,0),0) -> CL 8 12 10 | K62: =IFERROR(VLOOKUP($D62,'BASE DE DATOS'!$B:$I,7,0),0) -> 3017199935 | L62: =IFERROR(VLOOKUP($D62,'BASE DE DATOS'!$B:$I,8,0),0) -> 0 | M62: 488200 | N62: COSTO
A63: 45728 | B63: 289 | D63: =IFERROR(VLOOKUP($E63,'BASE DE DATOS'!$A:$I,2,0)," ") -> 14695845 | E63: MERCAFRUVER EL MAYORISTA | F63: =IFERROR(VLOOKUP($D63,'BASE DE DATOS'!$B:$I,2,0),0) -> EDELMIRA | G63: =IFERROR(VLOOKUP($D63,'BASE DE DATOS'!$B:$I,3,0),0) -> 0 | H63: =IFERROR(VLOOKUP($D63,'BASE DE DATOS'!$B:$I,4,0),0) -> MORALES | I63: =IFERROR(VLOOKUP($D63,'BASE DE DATOS'!$B:$I,5,0),0) -> ACOSTA | J63: =IFERROR(VLOOKUP($D63,'BASE DE DATOS'!$B:$I,6,0),0) -> ST 1 MZ 19 VILLAMARINA | K63: =IFERROR(VLOOKUP($D63,'BASE DE DATOS'!$B:$I,7,0),0) -> 3215223609 | L63: =IFERROR(VLOOKUP($D63,'BASE DE DATOS'!$B:$I,8,0),0) -> 0 | M63: 74327 | N63: COSTO
A64: 45728 | B64: 192 | D64: =IFERROR(VLOOKUP($E64,'BASE DE DATOS'!$A:$I,2,0)," ") -> 1112230545 | E64: salsamentaria | F64: =IFERROR(VLOOKUP($D64,'BASE DE DATOS'!$B:$I,2,0),0) -> 0 | G64: =IFERROR(VLOOKUP($D64,'BASE DE DATOS'!$B:$I,3,0),0) -> 0 | H64: =IFERROR(VLOOKUP($D64,'BASE DE DATOS'!$B:$I,4,0),0) -> 0 | I64: =IFERROR(VLOOKUP($D64,'BASE DE DATOS'!$B:$I,5,0),0) -> 0 | J64: =IFERROR(VLOOKUP($D64,'BASE DE DATOS'!$B:$I,6,0),0) -> 0 | K64: =IFERROR(VLOOKUP($D64,'BASE DE DATOS'!$B:$I,7,0),0) -> 3107292255 | L64: =IFERROR(VLOOKUP($D64,'BASE DE DATOS'!$B:$I,8,0),0) -> NO TIENE | M64: 553000 | N64: COSTO
A65: 45728 | B65: 0 | D65: =IFERROR(VLOOKUP($E65,'BASE DE DATOS'!$A:$I,2,0)," ") -> 0 | E65: BOLSAS PLASTICAS | F65: =IFERROR(VLOOKUP($D65,'BASE DE DATOS'!$B:$I,2,0),0) -> 0 | G65: =IFERROR(VLOOKUP($D65,'BASE DE DATOS'!$B:$I,3,0),0) -> 0 | H65: =IFERROR(VLOOKUP($D65,'BASE DE DATOS'!$B:$I,4,0),0) -> 0 | I65: =IFERROR(VLOOKUP($D65,'BASE DE DATOS'!$B:$I,5,0),0) -> 0 | J65: =IFERROR(VLOOKUP($D65,'BASE DE DATOS'!$B:$I,6,0),0) -> 0 | K65: =IFERROR(VLOOKUP($D65,'BASE DE DATOS'!$B:$I,7,0),0) -> 0 | L65: =IFERROR(VLOOKUP($D65,'BASE DE DATOS'!$B:$I,8,0),0) -> 0 | M65: 32500 | N65: GASTO
A66: 45729 | B66: 0 | D66: =IFERROR(VLOOKUP($E66,'BASE DE DATOS'!$A:$I,2,0)," ") -> 14695845 | E66: MERCAFRUVER EL MAYORISTA | F66: =IFERROR(VLOOKUP($D66,'BASE DE DATOS'!$B:$I,2,0),0) -> EDELMIRA | G66: =IFERROR(VLOOKUP($D66,'BASE DE DATOS'!$B:$I,3,0),0) -> 0 | H66: =IFERROR(VLOOKUP($D66,'BASE DE DATOS'!$B:$I,4,0),0) -> MORALES | I66: =IFERROR(VLOOKUP($D66,'BASE DE DATOS'!$B:$I,5,0),0) -> ACOSTA | J66: =IFERROR(VLOOKUP($D66,'BASE DE DATOS'!$B:$I,6,0),0) -> ST 1 MZ 19 VILLAMARINA | K66: =IFERROR(VLOOKUP($D66,'BASE DE DATOS'!$B:$I,7,0),0) -> 3215223609 | L66: =IFERROR(VLOOKUP($D66,'BASE DE DATOS'!$B:$I,8,0),0) -> 0 | M66: 55000 | N66: COSTO
A67: 45729 | B67: 4730 | D67: =IFERROR(VLOOKUP($E67,'BASE DE DATOS'!$A:$I,2,0)," ") -> 66929745 | E67: POLLOS EL SABOR | F67: =IFERROR(VLOOKUP($D67,'BASE DE DATOS'!$B:$I,2,0),0) -> MARTHA | G67: =IFERROR(VLOOKUP($D67,'BASE DE DATOS'!$B:$I,3,0),0) -> 0 | H67: =IFERROR(VLOOKUP($D67,'BASE DE DATOS'!$B:$I,4,0),0) -> 0 | I67: =IFERROR(VLOOKUP($D67,'BASE DE DATOS'!$B:$I,5,0),0) -> 0 | J67: =IFERROR(VLOOKUP($D67,'BASE DE DATOS'!$B:$I,6,0),0) -> CL 8 12 10 | K67: =IFERROR(VLOOKUP($D67,'BASE DE DATOS'!$B:$I,7,0),0) -> 3017199935 | L67: =IFERROR(VLOOKUP($D67,'BASE DE DATOS'!$B:$I,8,0),0) -> 0 | M67: 475600 | N67: COSTO
A68: 45730 | B68: 48777 | D68: =IFERROR(VLOOKUP($E68,'BASE DE DATOS'!$A:$I,2,0)," ") -> 900163982-1 | E68: ='BASE DE DATOS'!$A$158 -> PREMIOS Y PROMOCIONES EU | F68: =IFERROR(VLOOKUP($D68,'BASE DE DATOS'!$B:$I,2,0),0) -> KELLY | G68: =IFERROR(VLOOKUP($D68,'BASE DE DATOS'!$B:$I,3,0),0) -> 0 | H68: =IFERROR(VLOOKUP($D68,'BASE DE DATOS'!$B:$I,4,0),0) -> 0 | I68: =IFERROR(VLOOKUP($D68,'BASE DE DATOS'!$B:$I,5,0),0) -> 0 | J68: =IFERROR(VLOOKUP($D68,'BASE DE DATOS'!$B:$I,6,0),0) -> CALLE 14 8-36 | K68: =IFERROR(VLOOKUP($D68,'BASE DE DATOS'!$B:$I,7,0),0) -> 8899830 | L68: =IFERROR(VLOOKUP($D68,'BASE DE DATOS'!$B:$I,8,0),0) -> 0 | M68: 262000 | N68: GASTO
A69: 45727 | B69: 347729 | D69: =IFERROR(VLOOKUP($E69,'BASE DE DATOS'!$A:$I,2,0)," ") -> 815002459 | E69: ='BASE DE DATOS'!$A$94 -> MERCAPAVA SA | F69: =IFERROR(VLOOKUP($D69,'BASE DE DATOS'!$B:$I,2,0),0) -> NO TIENE | G69: =IFERROR(VLOOKUP($D69,'BASE DE DATOS'!$B:$I,3,0),0) -> NO TIENE | H69: =IFERROR(VLOOKUP($D69,'BASE DE DATOS'!$B:$I,4,0),0) -> NO TIENE | I69: =IFERROR(VLOOKUP($D69,'BASE DE DATOS'!$B:$I,5,0),0) -> NO TIENE | J69: =IFERROR(VLOOKUP($D69,'BASE DE DATOS'!$B:$I,6,0),0) -> CL 7 12 03 | K69: =IFERROR(VLOOKUP($D69,'BASE DE DATOS'!$B:$I,7,0),0) -> 3136831049 | L69: =IFERROR(VLOOKUP($D69,'BASE DE DATOS'!$B:$I,8,0),0) -> 0 | M69: 15450 | N69: GASTO
A70: 45730 | B70: 4795 | D70: =IFERROR(VLOOKUP($E70,'BASE DE DATOS'!$A:$I,2,0)," ") -> 66929745 | E70: POLLOS EL SABOR | F70: =IFERROR(VLOOKUP($D70,'BASE DE DATOS'!$B:$I,2,0),0) -> MARTHA | G70: =IFERROR(VLOOKUP($D70,'BASE DE DATOS'!$B:$I,3,0),0) -> 0 | H70: =IFERROR(VLOOKUP($D70,'BASE DE DATOS'!$B:$I,4,0),0) -> 0 | I70: =IFERROR(VLOOKUP($D70,'BASE DE DATOS'!$B:$I,5,0),0) -> 0 | J70: =IFERROR(VLOOKUP($D70,'BASE DE DATOS'!$B:$I,6,0),0) -> CL 8 12 10 | K70: =IFERROR(VLOOKUP($D70,'BASE DE DATOS'!$B:$I,7,0),0) -> 3017199935 | L70: =IFERROR(VLOOKUP($D70,'BASE DE DATOS'!$B:$I,8,0),0) -> 0 | M70: 478750 | N70: COSTO
A71: 45731 | B71: 4874 | D71: =IFERROR(VLOOKUP($E71,'BASE DE DATOS'!$A:$I,2,0)," ") -> 66929745 | E71: POLLOS EL SABOR | F71: =IFERROR(VLOOKUP($D71,'BASE DE DATOS'!$B:$I,2,0),0) -> MARTHA | G71: =IFERROR(VLOOKUP($D71,'BASE DE DATOS'!$B:$I,3,0),0) -> 0 | H71: =IFERROR(VLOOKUP($D71,'BASE DE DATOS'!$B:$I,4,0),0) -> 0 | I71: =IFERROR(VLOOKUP($D71,'BASE DE DATOS'!$B:$I,5,0),0) -> 0 | J71: =IFERROR(VLOOKUP($D71,'BASE DE DATOS'!$B:$I,6,0),0) -> CL 8 12 10 | K71: =IFERROR(VLOOKUP($D71,'BASE DE DATOS'!$B:$I,7,0),0) -> 3017199935 | L71: =IFERROR(VLOOKUP($D71,'BASE DE DATOS'!$B:$I,8,0),0) -> 0 | M71: 475600 | N71: COSTO
A72: 45730 | B72: 697107 | D72: =IFERROR(VLOOKUP($E72,'BASE DE DATOS'!$A:$I,2,0)," ") -> 890500726 | E72: NORTESANTANDEREANA DE GAS SA ESP | F72: =IFERROR(VLOOKUP($D72,'BASE DE DATOS'!$B:$I,2,0),0) -> NO TIENE | G72: =IFERROR(VLOOKUP($D72,'BASE DE DATOS'!$B:$I,3,0),0) -> NO TIENE | H72: =IFERROR(VLOOKUP($D72,'BASE DE DATOS'!$B:$I,4,0),0) -> NO TIENE | I72: =IFERROR(VLOOKUP($D72,'BASE DE DATOS'!$B:$I,5,0),0) -> NO TIENE | J72: =IFERROR(VLOOKUP($D72,'BASE DE DATOS'!$B:$I,6,0),0) -> 0 | K72: =IFERROR(VLOOKUP($D72,'BASE DE DATOS'!$B:$I,7,0),0) -> 3208899901 | L72: =IFERROR(VLOOKUP($D72,'BASE DE DATOS'!$B:$I,8,0),0) -> 0 | M72: 420000 | N72: COSTO
A73: 45730 | B73: 0 | D73: =IFERROR(VLOOKUP($E73,'BASE DE DATOS'!$A:$I,2,0)," ") -> 94303413 | E73: COLANTA | F73: =IFERROR(VLOOKUP($D73,'BASE DE DATOS'!$B:$I,2,0),0) -> GUSTAVO | G73: =IFERROR(VLOOKUP($D73,'BASE DE DATOS'!$B:$I,3,0),0) -> ADOLFO | H73: =IFERROR(VLOOKUP($D73,'BASE DE DATOS'!$B:$I,4,0),0) -> CAMPO | I73: =IFERROR(VLOOKUP($D73,'BASE DE DATOS'!$B:$I,5,0),0) -> TORRES | J73: =IFERROR(VLOOKUP($D73,'BASE DE DATOS'!$B:$I,6,0),0) -> CL 6 13 04 | K73: =IFERROR(VLOOKUP($D73,'BASE DE DATOS'!$B:$I,7,0),0) -> 3136595942 | L73: =IFERROR(VLOOKUP($D73,'BASE DE DATOS'!$B:$I,8,0),0) -> 0 | M73: 582000 | N73: COSTO
A74: 45731 | B74: 0 | D74: =IFERROR(VLOOKUP($E74,'BASE DE DATOS'!$A:$I,2,0)," ") -> 0 | E74: gastos varios caja/ descuadres | F74: =IFERROR(VLOOKUP($D74,'BASE DE DATOS'!$B:$I,2,0),0) -> 0 | G74: =IFERROR(VLOOKUP($D74,'BASE DE DATOS'!$B:$I,3,0),0) -> 0 | H74: =IFERROR(VLOOKUP($D74,'BASE DE DATOS'!$B:$I,4,0),0) -> 0 | I74: =IFERROR(VLOOKUP($D74,'BASE DE DATOS'!$B:$I,5,0),0) -> 0 | J74: =IFERROR(VLOOKUP($D74,'BASE DE DATOS'!$B:$I,6,0),0) -> 0 | K74: =IFERROR(VLOOKUP($D74,'BASE DE DATOS'!$B:$I,7,0),0) -> 0 | L74: =IFERROR(VLOOKUP($D74,'BASE DE DATOS'!$B:$I,8,0),0) -> 0 | M74: 94000 | N74: GASTO
A75: 45731 | B75: 10629 | D75: =IFERROR(VLOOKUP($E75,'BASE DE DATOS'!$A:$I,2,0)," ") -> 9017363446 | E75: ='BASE DE DATOS'!$A$141 -> DISTRIBUIDORA ZADAY SAS | F75: =IFERROR(VLOOKUP($D75,'BASE DE DATOS'!$B:$I,2,0),0) -> JORGE | G75: =IFERROR(VLOOKUP($D75,'BASE DE DATOS'!$B:$I,3,0),0) -> 0 | H75: =IFERROR(VLOOKUP($D75,'BASE DE DATOS'!$B:$I,4,0),0) -> MOSQUERA | I75: =IFERROR(VLOOKUP($D75,'BASE DE DATOS'!$B:$I,5,0),0) -> 0 | J75: =IFERROR(VLOOKUP($D75,'BASE DE DATOS'!$B:$I,6,0),0) -> MANZANA T CASA 17 MARIA 2 | K75: =IFERROR(VLOOKUP($D75,'BASE DE DATOS'!$B:$I,7,0),0) -> 3017939209 | L75: =IFERROR(VLOOKUP($D75,'BASE DE DATOS'!$B:$I,8,0),0) -> reporte@seitem.com | M75: 120000 | N75: COSTO
A76: 45731 | B76: 354966 | D76: =IFERROR(VLOOKUP($E76,'BASE DE DATOS'!$A:$I,2,0)," ") -> 815002459 | E76: MERCAPAVA SA | F76: =IFERROR(VLOOKUP($D76,'BASE DE DATOS'!$B:$I,2,0),0) -> NO TIENE | G76: =IFERROR(VLOOKUP($D76,'BASE DE DATOS'!$B:$I,3,0),0) -> NO TIENE | H76: =IFERROR(VLOOKUP($D76,'BASE DE DATOS'!$B:$I,4,0),0) -> NO TIENE | I76: =IFERROR(VLOOKUP($D76,'BASE DE DATOS'!$B:$I,5,0),0) -> NO TIENE | J76: =IFERROR(VLOOKUP($D76,'BASE DE DATOS'!$B:$I,6,0),0) -> CL 7 12 03 | K76: =IFERROR(VLOOKUP($D76,'BASE DE DATOS'!$B:$I,7,0),0) -> 3136831049 | L76: =IFERROR(VLOOKUP($D76,'BASE DE DATOS'!$B:$I,8,0),0) -> 0 | M76: 34450 | N76: COSTO
A77: 45732 | B77: 5042 | D77: =IFERROR(VLOOKUP($E77,'BASE DE DATOS'!$A:$I,2,0)," ") -> 66929745 | E77: POLLOS EL SABOR | F77: =IFERROR(VLOOKUP($D77,'BASE DE DATOS'!$B:$I,2,0),0) -> MARTHA | G77: =IFERROR(VLOOKUP($D77,'BASE DE DATOS'!$B:$I,3,0),0) -> 0 | H77: =IFERROR(VLOOKUP($D77,'BASE DE DATOS'!$B:$I,4,0),0) -> 0 | I77: =IFERROR(VLOOKUP($D77,'BASE DE DATOS'!$B:$I,5,0),0) -> 0 | J77: =IFERROR(VLOOKUP($D77,'BASE DE DATOS'!$B:$I,6,0),0) -> CL 8 12 10 | K77: =IFERROR(VLOOKUP($D77,'BASE DE DATOS'!$B:$I,7,0),0) -> 3017199935 | L77: =IFERROR(VLOOKUP($D77,'BASE DE DATOS'!$B:$I,8,0),0) -> 0 | M77: 486600 | N77: COSTO
A78: 45731 | B78: 348772 | D78: =IFERROR(VLOOKUP($E78,'BASE DE DATOS'!$A:$I,2,0)," ") -> 815002459 | E78: MERCAPAVA SA | F78: =IFERROR(VLOOKUP($D78,'BASE DE DATOS'!$B:$I,2,0),0) -> NO TIENE | G78: =IFERROR(VLOOKUP($D78,'BASE DE DATOS'!$B:$I,3,0),0) -> NO TIENE | H78: =IFERROR(VLOOKUP($D78,'BASE DE DATOS'!$B:$I,4,0),0) -> NO TIENE | I78: =IFERROR(VLOOKUP($D78,'BASE DE DATOS'!$B:$I,5,0),0) -> NO TIENE | J78: =IFERROR(VLOOKUP($D78,'BASE DE DATOS'!$B:$I,6,0),0) -> CL 7 12 03 | K78: =IFERROR(VLOOKUP($D78,'BASE DE DATOS'!$B:$I,7,0),0) -> 3136831049 | L78: =IFERROR(VLOOKUP($D78,'BASE DE DATOS'!$B:$I,8,0),0) -> 0 | M78: 20250 | N78: GASTO
A79: 15/0/2025 | B79: 0 | D79: =IFERROR(VLOOKUP($E79,'BASE DE DATOS'!$A:$I,2,0)," ") -> 0 | E79: LECHUGA | F79: =IFERROR(VLOOKUP($D79,'BASE DE DATOS'!$B:$I,2,0),0) -> 0 | G79: =IFERROR(VLOOKUP($D79,'BASE DE DATOS'!$B:$I,3,0),0) -> 0 | H79: =IFERROR(VLOOKUP($D79,'BASE DE DATOS'!$B:$I,4,0),0) -> 0 | I79: =IFERROR(VLOOKUP($D79,'BASE DE DATOS'!$B:$I,5,0),0) -> 0 | J79: =IFERROR(VLOOKUP($D79,'BASE DE DATOS'!$B:$I,6,0),0) -> 0 | K79: =IFERROR(VLOOKUP($D79,'BASE DE DATOS'!$B:$I,7,0),0) -> 0 | L79: =IFERROR(VLOOKUP($D79,'BASE DE DATOS'!$B:$I,8,0),0) -> 0 | M79: 15400 | N79: COSTO
A80: 45728 | B80: 64782 | D80: =IFERROR(VLOOKUP($E80,'BASE DE DATOS'!$A:$I,2,0)," ") -> 66931449 | E80: QUESERA Y SALSAMENTARIA LA MAXIMA | F80: =IFERROR(VLOOKUP($D80,'BASE DE DATOS'!$B:$I,2,0),0) -> NO TIENE | G80: =IFERROR(VLOOKUP($D80,'BASE DE DATOS'!$B:$I,3,0),0) -> NO TIENE | H80: =IFERROR(VLOOKUP($D80,'BASE DE DATOS'!$B:$I,4,0),0) -> NO TIENE | I80: =IFERROR(VLOOKUP($D80,'BASE DE DATOS'!$B:$I,5,0),0) -> NO TIENE | J80: =IFERROR(VLOOKUP($D80,'BASE DE DATOS'!$B:$I,6,0),0) -> CR 12 6 33 | K80: =IFERROR(VLOOKUP($D80,'BASE DE DATOS'!$B:$I,7,0),0) -> 2672346 | L80: =IFERROR(VLOOKUP($D80,'BASE DE DATOS'!$B:$I,8,0),0) -> NO TIENE | M80: 323000 | N80: GASTO
A81: 45731 | B81: 0 | D81: =IFERROR(VLOOKUP($E81,'BASE DE DATOS'!$A:$I,2,0)," ") -> 0 | E81: BOLSAS PLASTICAS | F81: =IFERROR(VLOOKUP($D81,'BASE DE DATOS'!$B:$I,2,0),0) -> 0 | G81: =IFERROR(VLOOKUP($D81,'BASE DE DATOS'!$B:$I,3,0),0) -> 0 | H81: =IFERROR(VLOOKUP($D81,'BASE DE DATOS'!$B:$I,4,0),0) -> 0 | I81: =IFERROR(VLOOKUP($D81,'BASE DE DATOS'!$B:$I,5,0),0) -> 0 | J81: =IFERROR(VLOOKUP($D81,'BASE DE DATOS'!$B:$I,6,0),0) -> 0 | K81: =IFERROR(VLOOKUP($D81,'BASE DE DATOS'!$B:$I,7,0),0) -> 0 | L81: =IFERROR(VLOOKUP($D81,'BASE DE DATOS'!$B:$I,8,0),0) -> 0 | M81: 25000 | N81: GASTO
A82: 45731 | B82: 0 | D82: =IFERROR(VLOOKUP($E82,'BASE DE DATOS'!$A:$I,2,0)," ") -> 0 | E82: gastos varios caja/ descuadres | F82: =IFERROR(VLOOKUP($D82,'BASE DE DATOS'!$B:$I,2,0),0) -> 0 | G82: =IFERROR(VLOOKUP($D82,'BASE DE DATOS'!$B:$I,3,0),0) -> 0 | H82: =IFERROR(VLOOKUP($D82,'BASE DE DATOS'!$B:$I,4,0),0) -> 0 | I82: =IFERROR(VLOOKUP($D82,'BASE DE DATOS'!$B:$I,5,0),0) -> 0 | J82: =IFERROR(VLOOKUP($D82,'BASE DE DATOS'!$B:$I,6,0),0) -> 0 | K82: =IFERROR(VLOOKUP($D82,'BASE DE DATOS'!$B:$I,7,0),0) -> 0 | L82: =IFERROR(VLOOKUP($D82,'BASE DE DATOS'!$B:$I,8,0),0) -> 0 | M82: 120000 | N82: GASTO
A83: 45727 | B83: 2681451 | D83: =IFERROR(VLOOKUP($E83,'BASE DE DATOS'!$A:$I,2,0)," ") -> 815003414 | E83: ='BASE DE DATOS'!$A$44 -> DISTRIVENTAS SAS | F83: =IFERROR(VLOOKUP($D83,'BASE DE DATOS'!$B:$I,2,0),0) -> NO TIENE | G83: =IFERROR(VLOOKUP($D83,'BASE DE DATOS'!$B:$I,3,0),0) -> NO TIENE | H83: =IFERROR(VLOOKUP($D83,'BASE DE DATOS'!$B:$I,4,0),0) -> NO TIENE | I83: =IFERROR(VLOOKUP($D83,'BASE DE DATOS'!$B:$I,5,0),0) -> NO TIENE | J83: =IFERROR(VLOOKUP($D83,'BASE DE DATOS'!$B:$I,6,0),0) -> CL 47 34C 45 B | K83: =IFERROR(VLOOKUP($D83,'BASE DE DATOS'!$B:$I,7,0),0) -> 3218057166 | L83: =IFERROR(VLOOKUP($D83,'BASE DE DATOS'!$B:$I,8,0),0) -> 0 | M83: 1507264 | N83: COSTO
A84: 45733 | B84: 0 | D84: =IFERROR(VLOOKUP($E84,'BASE DE DATOS'!$A:$I,2,0)," ") -> 0 | E84: =$E$38 -> MERCAFRUVER LA ECONOMIA demi pradera | F84: =IFERROR(VLOOKUP($D84,'BASE DE DATOS'!$B:$I,2,0),0) -> 0 | G84: =IFERROR(VLOOKUP($D84,'BASE DE DATOS'!$B:$I,3,0),0) -> 0 | H84: =IFERROR(VLOOKUP($D84,'BASE DE DATOS'!$B:$I,4,0),0) -> 0 | I84: =IFERROR(VLOOKUP($D84,'BASE DE DATOS'!$B:$I,5,0),0) -> 0 | J84: =IFERROR(VLOOKUP($D84,'BASE DE DATOS'!$B:$I,6,0),0) -> 0 | K84: =IFERROR(VLOOKUP($D84,'BASE DE DATOS'!$B:$I,7,0),0) -> 0 | L84: =IFERROR(VLOOKUP($D84,'BASE DE DATOS'!$B:$I,8,0),0) -> 0 | M84: 96000 | N84: COSTO
A85: 45736 | B85: 0 | D85: =IFERROR(VLOOKUP($E85,'BASE DE DATOS'!$A:$I,2,0)," ") -> 0 | E85: BOLSAS PLASTICAS | F85: =IFERROR(VLOOKUP($D85,'BASE DE DATOS'!$B:$I,2,0),0) -> 0 | G85: =IFERROR(VLOOKUP($D85,'BASE DE DATOS'!$B:$I,3,0),0) -> 0 | H85: =IFERROR(VLOOKUP($D85,'BASE DE DATOS'!$B:$I,4,0),0) -> 0 | I85: =IFERROR(VLOOKUP($D85,'BASE DE DATOS'!$B:$I,5,0),0) -> 0 | J85: =IFERROR(VLOOKUP($D85,'BASE DE DATOS'!$B:$I,6,0),0) -> 0 | K85: =IFERROR(VLOOKUP($D85,'BASE DE DATOS'!$B:$I,7,0),0) -> 0 | L85: =IFERROR(VLOOKUP($D85,'BASE DE DATOS'!$B:$I,8,0),0) -> 0 | M85: 26000 | N85: GASTO
A86: 45735 | B86: 250106 | D86: =IFERROR(VLOOKUP($E86,'BASE DE DATOS'!$A:$I,2,0)," ") -> 815002459 | E86: MERCAPAVA SA | F86: =IFERROR(VLOOKUP($D86,'BASE DE DATOS'!$B:$I,2,0),0) -> NO TIENE | G86: =IFERROR(VLOOKUP($D86,'BASE DE DATOS'!$B:$I,3,0),0) -> NO TIENE | H86: =IFERROR(VLOOKUP($D86,'BASE DE DATOS'!$B:$I,4,0),0) -> NO TIENE | I86: =IFERROR(VLOOKUP($D86,'BASE DE DATOS'!$B:$I,5,0),0) -> NO TIENE | J86: =IFERROR(VLOOKUP($D86,'BASE DE DATOS'!$B:$I,6,0),0) -> CL 7 12 03 | K86: =IFERROR(VLOOKUP($D86,'BASE DE DATOS'!$B:$I,7,0),0) -> 3136831049 | L86: =IFERROR(VLOOKUP($D86,'BASE DE DATOS'!$B:$I,8,0),0) -> 0 | M86: 70000 | N86: COSTO
A87: 45735 | B87: 359 | D87: =IFERROR(VLOOKUP($E87,'BASE DE DATOS'!$A:$I,2,0)," ") -> 1112230545 | E87: salsamentaria | F87: =IFERROR(VLOOKUP($D87,'BASE DE DATOS'!$B:$I,2,0),0) -> 0 | G87: =IFERROR(VLOOKUP($D87,'BASE DE DATOS'!$B:$I,3,0),0) -> 0 | H87: =IFERROR(VLOOKUP($D87,'BASE DE DATOS'!$B:$I,4,0),0) -> 0 | I87: =IFERROR(VLOOKUP($D87,'BASE DE DATOS'!$B:$I,5,0),0) -> 0 | J87: =IFERROR(VLOOKUP($D87,'BASE DE DATOS'!$B:$I,6,0),0) -> 0 | K87: =IFERROR(VLOOKUP($D87,'BASE DE DATOS'!$B:$I,7,0),0) -> 3107292255 | L87: =IFERROR(VLOOKUP($D87,'BASE DE DATOS'!$B:$I,8,0),0) -> NO TIENE | M87: 512500 | N87: GASTO
A88: 45735 | B88: 0 | D88: =IFERROR(VLOOKUP($E88,'BASE DE DATOS'!$A:$I,2,0)," ") -> 0 | E88: gastos varios caja/ descuadres | F88: =IFERROR(VLOOKUP($D88,'BASE DE DATOS'!$B:$I,2,0),0) -> 0 | G88: =IFERROR(VLOOKUP($D88,'BASE DE DATOS'!$B:$I,3,0),0) -> 0 | H88: =IFERROR(VLOOKUP($D88,'BASE DE DATOS'!$B:$I,4,0),0) -> 0 | I88: =IFERROR(VLOOKUP($D88,'BASE DE DATOS'!$B:$I,5,0),0) -> 0 | J88: =IFERROR(VLOOKUP($D88,'BASE DE DATOS'!$B:$I,6,0),0) -> 0 | K88: =IFERROR(VLOOKUP($D88,'BASE DE DATOS'!$B:$I,7,0),0) -> 0 | L88: =IFERROR(VLOOKUP($D88,'BASE DE DATOS'!$B:$I,8,0),0) -> 0 | M88: 10000 | N88: GASTO
A89: 45735 | B89: 5153 | D89: =IFERROR(VLOOKUP($E89,'BASE DE DATOS'!$A:$I,2,0)," ") -> 66929745 | E89: POLLOS EL SABOR | F89: =IFERROR(VLOOKUP($D89,'BASE DE DATOS'!$B:$I,2,0),0) -> MARTHA | G89: =IFERROR(VLOOKUP($D89,'BASE DE DATOS'!$B:$I,3,0),0) -> 0 | H89: =IFERROR(VLOOKUP($D89,'BASE DE DATOS'!$B:$I,4,0),0) -> 0 | I89: =IFERROR(VLOOKUP($D89,'BASE DE DATOS'!$B:$I,5,0),0) -> 0 | J89: =IFERROR(VLOOKUP($D89,'BASE DE DATOS'!$B:$I,6,0),0) -> CL 8 12 10 | K89: =IFERROR(VLOOKUP($D89,'BASE DE DATOS'!$B:$I,7,0),0) -> 3017199935 | L89: =IFERROR(VLOOKUP($D89,'BASE DE DATOS'!$B:$I,8,0),0) -> 0 | M89: 483500 | N89: COSTO
A90: 45735 | B90: 0 | D90: =IFERROR(VLOOKUP($E90,'BASE DE DATOS'!$A:$I,2,0)," ") -> 14695845 | E90: MERCAFRUVER EL MAYORISTA | F90: =IFERROR(VLOOKUP($D90,'BASE DE DATOS'!$B:$I,2,0),0) -> EDELMIRA | G90: =IFERROR(VLOOKUP($D90,'BASE DE DATOS'!$B:$I,3,0),0) -> 0 | H90: =IFERROR(VLOOKUP($D90,'BASE DE DATOS'!$B:$I,4,0),0) -> MORALES | I90: =IFERROR(VLOOKUP($D90,'BASE DE DATOS'!$B:$I,5,0),0) -> ACOSTA | J90: =IFERROR(VLOOKUP($D90,'BASE DE DATOS'!$B:$I,6,0),0) -> ST 1 MZ 19 VILLAMARINA | K90: =IFERROR(VLOOKUP($D90,'BASE DE DATOS'!$B:$I,7,0),0) -> 3215223609 | L90: =IFERROR(VLOOKUP($D90,'BASE DE DATOS'!$B:$I,8,0),0) -> 0 | M90: 55000 | N90: COSTO
A91: 45734 | B91: 0 | D91: =IFERROR(VLOOKUP($E91,'BASE DE DATOS'!$A:$I,2,0)," ") -> 94303413 | E91: COLANTA | F91: =IFERROR(VLOOKUP($D91,'BASE DE DATOS'!$B:$I,2,0),0) -> GUSTAVO | G91: =IFERROR(VLOOKUP($D91,'BASE DE DATOS'!$B:$I,3,0),0) -> ADOLFO | H91: =IFERROR(VLOOKUP($D91,'BASE DE DATOS'!$B:$I,4,0),0) -> CAMPO | I91: =IFERROR(VLOOKUP($D91,'BASE DE DATOS'!$B:$I,5,0),0) -> TORRES | J91: =IFERROR(VLOOKUP($D91,'BASE DE DATOS'!$B:$I,6,0),0) -> CL 6 13 04 | K91: =IFERROR(VLOOKUP($D91,'BASE DE DATOS'!$B:$I,7,0),0) -> 3136595942 | L91: =IFERROR(VLOOKUP($D91,'BASE DE DATOS'!$B:$I,8,0),0) -> 0 | M91: 582000 | N91: COSTO
A92: 45734 | B92: 0 | D92: =IFERROR(VLOOKUP($E92,'BASE DE DATOS'!$A:$I,2,0)," ") -> 0 | E92: aguacates | F92: =IFERROR(VLOOKUP($D92,'BASE DE DATOS'!$B:$I,2,0),0) -> 0 | G92: =IFERROR(VLOOKUP($D92,'BASE DE DATOS'!$B:$I,3,0),0) -> 0 | H92: =IFERROR(VLOOKUP($D92,'BASE DE DATOS'!$B:$I,4,0),0) -> 0 | I92: =IFERROR(VLOOKUP($D92,'BASE DE DATOS'!$B:$I,5,0),0) -> 0 | J92: =IFERROR(VLOOKUP($D92,'BASE DE DATOS'!$B:$I,6,0),0) -> 0 | K92: =IFERROR(VLOOKUP($D92,'BASE DE DATOS'!$B:$I,7,0),0) -> 0 | L92: =IFERROR(VLOOKUP($D92,'BASE DE DATOS'!$B:$I,8,0),0) -> 0 | M92: 240000 | N92: COSTO
A93: 45736 | B93: 0 | D93: =IFERROR(VLOOKUP($E93,'BASE DE DATOS'!$A:$I,2,0)," ") -> 14695845 | E93: MERCAFRUVER EL MAYORISTA | F93: =IFERROR(VLOOKUP($D93,'BASE DE DATOS'!$B:$I,2,0),0) -> EDELMIRA | G93: =IFERROR(VLOOKUP($D93,'BASE DE DATOS'!$B:$I,3,0),0) -> 0 | H93: =IFERROR(VLOOKUP($D93,'BASE DE DATOS'!$B:$I,4,0),0) -> MORALES | I93: =IFERROR(VLOOKUP($D93,'BASE DE DATOS'!$B:$I,5,0),0) -> ACOSTA | J93: =IFERROR(VLOOKUP($D93,'BASE DE DATOS'!$B:$I,6,0),0) -> ST 1 MZ 19 VILLAMARINA | K93: =IFERROR(VLOOKUP($D93,'BASE DE DATOS'!$B:$I,7,0),0) -> 3215223609 | L93: =IFERROR(VLOOKUP($D93,'BASE DE DATOS'!$B:$I,8,0),0) -> 0 | M93: 65000 | N93: COSTO
A94: 45736 | B94: 5221 | D94: =IFERROR(VLOOKUP($E94,'BASE DE DATOS'!$A:$I,2,0)," ") -> 66929745 | E94: POLLOS EL SABOR | F94: =IFERROR(VLOOKUP($D94,'BASE DE DATOS'!$B:$I,2,0),0) -> MARTHA | G94: =IFERROR(VLOOKUP($D94,'BASE DE DATOS'!$B:$I,3,0),0) -> 0 | H94: =IFERROR(VLOOKUP($D94,'BASE DE DATOS'!$B:$I,4,0),0) -> 0 | I94: =IFERROR(VLOOKUP($D94,'BASE DE DATOS'!$B:$I,5,0),0) -> 0 | J94: =IFERROR(VLOOKUP($D94,'BASE DE DATOS'!$B:$I,6,0),0) -> CL 8 12 10 | K94: =IFERROR(VLOOKUP($D94,'BASE DE DATOS'!$B:$I,7,0),0) -> 3017199935 | L94: =IFERROR(VLOOKUP($D94,'BASE DE DATOS'!$B:$I,8,0),0) -> 0 | M94: 474000 | N94: COSTO
A95: 45736 | B95: 10567 | D95: =IFERROR(VLOOKUP($E95,'BASE DE DATOS'!$A:$I,2,0)," ") -> 9017363446 | E95: DISTRIBUIDORA ZADAY SAS | F95: =IFERROR(VLOOKUP($D95,'BASE DE DATOS'!$B:$I,2,0),0) -> JORGE | G95: =IFERROR(VLOOKUP($D95,'BASE DE DATOS'!$B:$I,3,0),0) -> 0 | H95: =IFERROR(VLOOKUP($D95,'BASE DE DATOS'!$B:$I,4,0),0) -> MOSQUERA | I95: =IFERROR(VLOOKUP($D95,'BASE DE DATOS'!$B:$I,5,0),0) -> 0 | J95: =IFERROR(VLOOKUP($D95,'BASE DE DATOS'!$B:$I,6,0),0) -> MANZANA T CASA 17 MARIA 2 | K95: =IFERROR(VLOOKUP($D95,'BASE DE DATOS'!$B:$I,7,0),0) -> 3017939209 | L95: =IFERROR(VLOOKUP($D95,'BASE DE DATOS'!$B:$I,8,0),0) -> reporte@seitem.com | M95: 120000 | N95: COSTO
A96: 45736 | B96: 197153355 | D96: =IFERROR(VLOOKUP($E96,'BASE DE DATOS'!$A:$I,2,0)," ") -> 8903990328 | E96: ='BASE DE DATOS'!$A$144 -> ACUAVALLE S.A E.S.P | F96: =IFERROR(VLOOKUP($D96,'BASE DE DATOS'!$B:$I,2,0),0) -> JORGE | G96: =IFERROR(VLOOKUP($D96,'BASE DE DATOS'!$B:$I,3,0),0) -> 0 | H96: =IFERROR(VLOOKUP($D96,'BASE DE DATOS'!$B:$I,4,0),0) -> RODRIGUEZ | I96: =IFERROR(VLOOKUP($D96,'BASE DE DATOS'!$B:$I,5,0),0) -> 0 | J96: =IFERROR(VLOOKUP($D96,'BASE DE DATOS'!$B:$I,6,0),0) -> 0 | K96: =IFERROR(VLOOKUP($D96,'BASE DE DATOS'!$B:$I,7,0),0) -> 0 | L96: =IFERROR(VLOOKUP($D96,'BASE DE DATOS'!$B:$I,8,0),0) -> 0 | M96: 90160 | N96: SERVICIOS
A97: 45737 | B97: 6388 | D97: =IFERROR(VLOOKUP($E97,'BASE DE DATOS'!$A:$I,2,0)," ") -> 66660257 | E97: DISOIL | F97: =IFERROR(VLOOKUP($D97,'BASE DE DATOS'!$B:$I,2,0),0) -> 0 | G97: =IFERROR(VLOOKUP($D97,'BASE DE DATOS'!$B:$I,3,0),0) -> 0 | H97: =IFERROR(VLOOKUP($D97,'BASE DE DATOS'!$B:$I,4,0),0) -> 0 | I97: =IFERROR(VLOOKUP($D97,'BASE DE DATOS'!$B:$I,5,0),0) -> 0 | J97: =IFERROR(VLOOKUP($D97,'BASE DE DATOS'!$B:$I,6,0),0) -> CL 21 31 37 | K97: =IFERROR(VLOOKUP($D97,'BASE DE DATOS'!$B:$I,7,0),0) -> 3005547057 | L97: =IFERROR(VLOOKUP($D97,'BASE DE DATOS'!$B:$I,8,0),0) -> 0 | M97: 438000 | N97: SERVICIOS
A98: 45737 | B98: 16 | D98: =IFERROR(VLOOKUP($E98,'BASE DE DATOS'!$A:$I,2,0)," ") -> 14695845 | E98: MERCAFRUVER EL MAYORISTA | F98: =IFERROR(VLOOKUP($D98,'BASE DE DATOS'!$B:$I,2,0),0) -> EDELMIRA | G98: =IFERROR(VLOOKUP($D98,'BASE DE DATOS'!$B:$I,3,0),0) -> 0 | H98: =IFERROR(VLOOKUP($D98,'BASE DE DATOS'!$B:$I,4,0),0) -> MORALES | I98: =IFERROR(VLOOKUP($D98,'BASE DE DATOS'!$B:$I,5,0),0) -> ACOSTA | J98: =IFERROR(VLOOKUP($D98,'BASE DE DATOS'!$B:$I,6,0),0) -> ST 1 MZ 19 VILLAMARINA | K98: =IFERROR(VLOOKUP($D98,'BASE DE DATOS'!$B:$I,7,0),0) -> 3215223609 | L98: =IFERROR(VLOOKUP($D98,'BASE DE DATOS'!$B:$I,8,0),0) -> 0 | M98: 70000 | N98: COSTO
A99: 45737 | B99: 697108 | D99: =IFERROR(VLOOKUP($E99,'BASE DE DATOS'!$A:$I,2,0)," ") -> 890500726 | E99: NORTESANTANDEREANA DE GAS SA ESP | F99: =IFERROR(VLOOKUP($D99,'BASE DE DATOS'!$B:$I,2,0),0) -> NO TIENE | G99: =IFERROR(VLOOKUP($D99,'BASE DE DATOS'!$B:$I,3,0),0) -> NO TIENE | H99: =IFERROR(VLOOKUP($D99,'BASE DE DATOS'!$B:$I,4,0),0) -> NO TIENE | I99: =IFERROR(VLOOKUP($D99,'BASE DE DATOS'!$B:$I,5,0),0) -> NO TIENE | J99: =IFERROR(VLOOKUP($D99,'BASE DE DATOS'!$B:$I,6,0),0) -> 0 | K99: =IFERROR(VLOOKUP($D99,'BASE DE DATOS'!$B:$I,7,0),0) -> 3208899901 | L99: =IFERROR(VLOOKUP($D99,'BASE DE DATOS'!$B:$I,8,0),0) -> 0 | M99: 420000 | N99: SERVICIOS
A100: 45737 | B100: 0 | D100: =IFERROR(VLOOKUP($E100,'BASE DE DATOS'!$A:$I,2,0)," ") -> 1112230545 | E100: salsamentaria | F100: =IFERROR(VLOOKUP($D100,'BASE DE DATOS'!$B:$I,2,0),0) -> 0 | G100: =IFERROR(VLOOKUP($D100,'BASE DE DATOS'!$B:$I,3,0),0) -> 0 | H100: =IFERROR(VLOOKUP($D100,'BASE DE DATOS'!$B:$I,4,0),0) -> 0 | I100: =IFERROR(VLOOKUP($D100,'BASE DE DATOS'!$B:$I,5,0),0) -> 0 | J100: =IFERROR(VLOOKUP($D100,'BASE DE DATOS'!$B:$I,6,0),0) -> 0 | K100: =IFERROR(VLOOKUP($D100,'BASE DE DATOS'!$B:$I,7,0),0) -> 3107292255 | L100: =IFERROR(VLOOKUP($D100,'BASE DE DATOS'!$B:$I,8,0),0) -> NO TIENE | M100: 11200 | N100: GASTO
...

Sheet INGRESOS
A1: INGRESOS MARZO 2025
A3: FECHA | B3: CAJA | C3: BANCOS | D3: TARJETA CR
A4: 45717 | B4: 3797500 | C4: 1069500 | D4: 117900
A5: 45718 | B5: 3452500 | C5: 411000 | D5: 58150
A6: 45719
A7: 45720
A8: 45721 | B8: 664500 | C8: 128500 | D8: 12350
A9: 45722 | B9: 1468500 | C9: 246000 | D9: 0
A10: 45723 | B10: 1653500 | C10: 504000 | D10: 152400
A11: 45724 | B11: 4781000 | C11: 1005500 | D11: 111200
A12: 45725 | B12: 3348000 | C12: 945500 | D12: 118900
A13: 45726
A14: 45727
A15: 45728 | B15: 952500 | C15: 246500 | D15: 62800
A16: 45729 | B16: 666000 | C16: 271500 | D16: 19550
A17: 45730 | B17: 1316000 | C17: 613500 | D17: 97300
A18: 45731 | B18: 3208500 | C18: 554500 | D18: 181200
A19: 45732 | B19: 2513000 | C19: 942500 | D19: 96000
A20: 45733
A21: 45734
A22: 45735 | B22: 1110000 | C22: 497000 | D22: 37050
A23: 45736 | B23: 976000 | C23: 386000 | D23: 90100
A24: 45737 | B24: 1315600 | C24: 561000 | D24: 53450
A25: 45738 | B25: 3812500 | C25: 597000 | D25: 132800
A26: 45739 | B26: 3157000 | C26: 447500 | D26: 146750
A27: 45740 | B27: 2350000 | C27: 868500 | D27: 155000
A28: 45741
A29: 45742
A30: 45743 | B30: 1124000 | C30: 224500 | D30: 0
A31: 45744 | B31: 2299800 | C31: 1102500 | D31: 157050
A32: 45745 | B32: 6007200 | C32: 1209400 | D32: 400550
A33: 45746 | B33: 4439900 | C33: 1762200 | D33: 155200
A34: 45747 | B34: 1579300 | C34: 665800 | D34: 92350
A36: TOTAL | B36: =SUM(B4:B34) -> 55992800 | C36: =SUM(C4:C34) -> 15259900 | D36: =SUM(D4:D34) -> 2448050 | F36: =SUM(B36:D36) -> 73700750

Sheet BASE DE DATOS
A1: RAZON SOCIAL | B1: NIT | C1: PRIMER NOMBRE | D1: SEGUNDO NOMBRE | E1: PRIMER APELLIDO | F1: SEGUNDOAPELLIDO | G1: DIRECCION | H1: TELEFONO | I1: Correo | J1: TIPO
A2: AGENCIA LUPA SAS | B2: 901086443 | G2: CR 31 9C70 | H2: 3165288931 | J2: COSTO
A3: aguacates | J3: COSTO
A4: =CONCATENATE(C4," ",D4," ",E4," ",F4) -> ALBA NELLY VALDES CUERO | B4: 66885892 | C4: ALBA | D4: NELLY | E4: VALDES | F4: CUERO | G4: CL 10 17 25 | H4: 3225908464 | J4: EMPLEADO
A5: APORTES EN LINEA | B5: 900147238 | G5: CR 14ª No. 101-47 | H5: 4853939 | J5: SEG SOCIAL
A6: BARRA ESTANCO EL BARRIL DE LA SEXTA | B6: 29705164 | C6: DIANA | D6: MARIA | E6: ARIAS | F6: ECHAVARRIA | G6: CL 6 11 03 | H6: 3163471484 | J6: COSTO
A7: BIMBO DE COLOMBIA SA | B7: 830002366 | C7: NO TIENE | D7: NO TIENE | E7: NO TIENE | F7: NO TIENE | G7: KM 12 AUTOPISTA MEDELLIN | J7: COSTO
A8: BOLSAS PLASTICAS | J8: GASTO
A9: =CONCATENATE(C9," ",D9," ",E9," ",F9) -> BREINER RESTREPO | C9: BREINER | E9: RESTREPO | J9: EMPLEADO
A10: BRENDA GOMEZ | B10: 1112219602 | C10: BRENDA | E10: GOMEZ | G10: CR 10 CASA 24 | H10: 3116075631 | J10: EMPLEADO
A11: CAJAS MORSA | J11: COSTO
A12: =CONCATENATE(C12," ",D12," ",E12," ",F12) -> CAMILA GOMEZ | B12: 1113696548 | C12: CAMILA | E12: GOMEZ | G12: CL 4 3 27 | H12: 3113807982 | J12: EMPLEADO
A13: CELSIA COLOMBIA SA ESP | B13: 800249860 | C13: NO TIENE | D13: NO TIENE | E13: NO TIENE | F13: NO TIENE | G13: CL 15 29 30 | H13: 3210000 | I13: servicioalcliente@celsia.com | J13: SERVICIOS
A14: CENTRO DIAGNOSTICO AUTOMOTOR PARAISO SAS | B14: 900560653 | G14: TV 30 1 271 | H14: 2755717 | I14: cdaparaisocsa@gmail.com | J14: GASTO
A15: CES RED LOGISTICA SAS | B15: 901265547 | G15: CL 77 16A 15 | H15: 3163927576 | I15: notificaciones@cesred.com | J15: GASTO
A16: CESAR AUGUSTO SASTOQUE | B16: 1112223387 | C16: CESAR | D16: AUGUSTO | E16: SASTOQUE | G16: CL 6 12 84 | H16: 3188276966 | J16: EMPLEADO
A17: CINDY JOHANA AGUILAR | B17: 1193134535 | C17: CINDY | D17: JOHANA | E17: AGUILAR | G17: MZ 33 CASA 15 | H17: 3235481899 | J17: EMPLEADO
A18: COCO LOKO PIÑATERIA Y JUGUETERIA | B18: 29707452 | J18: GASTO
A19: COLANTA | B19: 94303413 | C19: GUSTAVO | D19: ADOLFO | E19: CAMPO | F19: TORRES | G19: CL 6 13 04 | H19: 3136595942 | J19: COSTO
A20: COLOMBIA TELECOMUNICACIONES SA | B20: 830122566 | J20: SERVICIOS
A21: COMCEL SA | B21: 800153993 | C21: NO TIENE | D21: NO TIENE | E21: NO TIENE | F21: NO TIENE | J21: SERVICIOS
A22: COMERCIALIZADORA GARCIA Y ASOCIADOS | B22: 901249410 | G22: CL 27 25 26 | H22: 2856473 | J22: COSTO
A23: COMERCIALIZADORA H&F | B23: 901344319 | G23: CR 11 7 52 | J23: COSTO
A24: COMERCIALIZADORA MARDEN LTDA | B24: 800004599 | G24: MARDEN BOSQUE | J24: GASTO
A25: COMERCIALIZADORA SASTOQUE | H25: 3178278606 | J25: COSTO
A26: CRISTALERIA EL REMATE DE LA 11 | B26: 10085753 | G26: CR 11 7 08 | H26: 3163314926 | J26: GASTO
A27: =CONCATENATE(C27," ",D27," ",E27," ",F27) -> CRISTIAN GALLEGO | C27: CRISTIAN | E27: GALLEGO | J27: EMPLEADO
A28: CRISTIAN ANDRES MOSQUERA CIRO | B28: 1112224034 | C28: CRISTIAN | D28: ANDRES | E28: MOSQUERA | F28: CIRO | G28: CL 2B TV 13 33 | H28: 3104657035 | J28: EMPLEADO
A29: CRISTIAN YAHIR GUERRERO GIRON | B29: 1006218066 | C29: CRISTIAN | D29: YAHIR | E29: GUERRERO | F29: GIRON | G29: CL 10 14 63 | H29: 3215272745 | J29: EMPLEADO
A30: CRISTINA ALEJANDRA SINISTERRA PALOMINO | B30: 1006035547 | C30: CRISTINA | D30: ALEJANDRA | E30: SINISTERRA | F30: PALOMINO | G30: CR 13 1B 38 | H30: 3122529315 | J30: EMPLEADO
A31: CUATRO ESQUINAS DON HERNAN | B31: 12911666 | C31: FREDY | D31: HERNAN | E31: CABEZAS | G31: CR 15 CL 9 CASA 28 | H31: 3216713381 | J31: PATROCINIO
A32: D1 SAS | B32: 900276962 | H32: 18000120201 | J32: GASTO
A33: =CONCATENATE(C33," ",D33," ",E33," ",F33) -> DANEISY GARCIA | B33: 1003152815 | C33: DANEISY | E33: GARCIA | G33: CL 10 14 48 | H33: 3103083893 | J33: EMPLEADO
A34: DANNA SOALRTE ROJAS | B34: 1114621431 | C34: DANNA | E34: SOALRTE | F34: ROJAS | G34: CR 3 5 38 | H34: 3027634803 | J34: EMPLEADO
A35: DARLING MARIANA ROJAS GONZALES | B35: 1114621502 | C35: DARLING | D35: MARIANA | E35: ROJAS | F35: GONZALES | G35: MZ C CASA 21 LA LORENA | H35: 3217975473 | J35: EMPLEADO
A36: DARSALUD DROGUERIA | B36: 835000779 | G36: CR 8 10 08 | H36: 2757817 | J36: GASTO
A37: DEPOSITO PRINCIPAL DE DROGAS LTDA | B37: 860514592 | J37: GASTO
A38: DISOIL | B38: 66660257 | G38: CL 21 31 37 | H38: 3005547057 | J38: COSTO
A39: DISOIL | B39: 66660257 | G39: DG 29A T7A 155 | H39: 3005547057 | J39: COSTO
A40: DISTRIBUCIONES JACOTA ZOMAC SAS | B40: 901473419 | G40: CR 10 5 32 | H40: 3147560646 | I40: jacota.distribuciones@outlook.com | J40: COSTO
A41: DISTRIBUIDORA POLLO ARIAS | B41: 1006216746 | C41: NATALIA | E41: ARIAS | F41: VARON | G41: CL 8 CR 12 ESQ | H41: 3214293700 | J41: COSTO
A42: DISTRICERVEZAS JG | B42: 6406403 | C42: NO TIENE | D42: NO TIENE | E42: NO TIENE | F42: NO TIENE | G42: CR 12 5 57 | H42: 2670572 | J42: COSTO
A43: DISTRIMOTOS PALMIRA SAS | B43: 900990648 | G43: CR 33 A 31 24 | H43: 2873726 | J43: GASTO
A44: DISTRIVENTAS SAS | B44: 815003414 | C44: NO TIENE | D44: NO TIENE | E44: NO TIENE | F44: NO TIENE | G44: CL 47 34C 45 B | H44: 3218057166 | J44: COSTO
A45: DROGUERIA LAS FLORES PRADERA | B45: 16856459 | C45: EDUARDO | E45: PERILLA | G45: CR 10 5 42 | H45: 2670487 | J45: GASTO
A46: DROGUERIA PANAMERICANA | B46: 860026130 | G46: CR 19 34 02 | H46: 3207503292 | J46: GASTO
A47: DROGUERIA SAN PABLO | B47: 860026123 | G47: CL 7 12 55 | H47: 2670003 | J47: GASTO
A48: EL MACHETAZO DE PALMIRA SAS | B48: 900433601 | G48: CL 29 25 28 | H48: 2855584 | J48: GASTO
A49: EL REGALON | G49: CL 5 8 56 | J49: GASTO
A50: ELECTROFERREMOS | B50: 6403376 | C50: JOSE | D50: ORLANDO | E50: MOSQUERA | G50: CR 11 8 08 | H50: 3217862287 | J50: GASTO
A51: enterate pradera | J51: PUBLICIDAD
A52: ESPECIAS Y DELICIAS BLANQUITA SAS | B52: 901398473 | G52: CR 26 27 46 | H52: 3166151651 | J52: COSTO
A53: FAMA LA SUPER 2000 | B53: 94302384 | C53: NO TIENE | D53: NO TIENE | E53: NO TIENE | F53: NO TIENE | G53: CL 7 9 60 | H53: 3187141443 | I53: famalasuper2000@gmail.com | J53: COSTO
A54: FAMA LA SUPER 2000 | B54: 94302384 | C54: NO TIENE | D54: NO TIENE | E54: NO TIENE | F54: NO TIENE | G54: CL 7 9 58 | H54: 3187141441 | I54: famalasuper2000@gmail.com | J54: COSTO
A55: FAMA LA SUPER 2000 | B55: 94302384 | C55: NO TIENE | D55: NO TIENE | E55: NO TIENE | F55: NO TIENE | G55: CL 7 9 59 | H55: 3187141442 | I55: famalasuper2000@gmail.com | J55: COSTO
A56: FERRETERIA PAVA | B56: 800020724 | G56: CL 5 10 39 | H56: 3117691009 | J56: GASTO
A57: FIDEICOMISO PA | B57: 830054539 | J57: GASTO
A58: gastos varios caja/ descuadres | C58: NO TIENE | D58: NO TIENE | E58: NO TIENE | F58: NO TIENE | J58: 0
A59: GERMAN TOVAR | B59: 4712068 | C59: GERMAN | E59: TOVAR | G59: CL 6 15 03 | H59: 3168117423 | J59: GASTO
A60: GLADYS BENITES | B60: 43738068 | C60: GLADYS | E60: BENITES | G60: CL 4 11 64 | H60: 3205492923 | J60: EMPLEADO
A61: GRUPO HOTELERO LA 70 ESTADIO | B61: 901249425 | G61: CR 69 A 42 30 | H61: 3229660 | J61: GASTO
A62: HARRY PLOTTER | G62: CR 30 28 66 | H62: 2855879 | J62: PUBLICIDAD
A63: HERNAN DARIO VARGAS NUÑEZ | B63: 1006352061 | C63: HERNAN | D63: DARIO | E63: VARGAS | F63: NUÑEZ | G63: CL 8 2 85 | H63: 3127898693 | J63: EMPLEADO
A64: HUEVOS Y GRANOS LA GALERIA | C64: CAJAS | G64: CR 12 8 15 | J64: COSTO
A65: INVERSIONES DJC SAS | B65: 901148686 | C65: PAKTO | G65: CL 45 E 71 04 IN 301 | H65: 3146807330 | J65: COSTO
A66: INVERSIONES PAEZ & MOLINA SAS | B66: 901565330 | G66: CR 12 6 23 | H66: 3154397571 | J66: GASTO
A67: INVERSIONES PAEZ &SANCHEZ SAS | B67: 901565330 | G67: CR 12 6 23 | H67: 3154397571 | J67: GASTO
A68: JERONIMO MARTINS COLOMBIA SAS | B68: 900480569 | C68: NO TIENE | D68: NO TIENE | E68: NO TIENE | F68: NO TIENE | G68: CL 7 11 21 | J68: COSTO
A69: JESSICA MERA | B69: 1007836613 | C69: JESSICA | E69: MERA | G69: CR 15 6 68 | H69: 3172844289 | J69: EMPLEADO
A70: =CONCATENATE(C70," ",D70," ",E70," ",F70) -> JUAN JOSE GALLEGO BENITEZ | B70: 1033176251 | C70: JUAN | D70: JOSE | E70: GALLEGO | F70: BENITEZ | G70: CL 4 11 64 | H70: 3205492923 | J70: EMPLEADO
A71: JULIAN ANDRES MUÑOZ | B71: 1114623181 | C71: JULIAN | D71: ANDRES | E71: MUÑOZ | G71: DG 6T2 A48 | H71: 3147587239 | J71: EMPLEADO
A72: =CONCATENATE(C72," ",D72," ",E72," ",F72) -> KATHALINA RANGEL | C72: KATHALINA | E72: RANGEL | J72: EMPLEADO
A73: =CONCATENATE(C73," ",D73," ",E73," ",F73) -> KEVIN PADILLA | B73: 1112231065 | C73: KEVIN | E73: PADILLA | G73: CR 10 9 57 | H73: 3207520719 | J73: EMPLEADO
A74: KINGMAN CELULARES | B74: 1113663529 | G74: CL 31 25 45 | H74: 3158223466 | J74: GASTO
A75: LA BONANZA MERKAFRUVER | B75: 1112226660 | C75: NO TIENE | D75: NO TIENE | E75: NO TIENE | F75: NO TIENE | G75: CL 7 7 33 | H75: 3182729196 | J75: COSTO
A76: LA BONANZA MERKAFRUVER | B76: 1112226661 | C76: NO TIENE | D76: NO TIENE | E76: NO TIENE | F76: NO TIENE | G76: CL 7 7 34 | H76: 3182729197 | J76: COSTO
A77: LA CASA DEL PANDEBONO | B77: 1144199443 | H77: 2691961 | J77: GASTO
A78: LA MAYORISTA FRUVER | B78: 1113978270 | G78: SC 1 MZ 19 VILLAMARINA | H78: 3215223611 | J78: COSTO
A79: LA MAYORISTA FRUVER | B79: 1113978269 | G79: SC 1 MZ 19 VILLAMARINA | H79: 3215223610 | J79: COSTO
A80: LA MAYORISTA FRUVER | B80: 1113978268 | G80: SC 1 MZ 19 VILLAMARINA | H80: 3215223609 | J80: COSTO
A81: LA REGALIA DE PRADERA | B81: 52838272 | J81: GASTO
A82: LA ROCA IMPRESIÓN Y DISEÑO | B82: 1144204314 | G82: CL 21 5 79 | H82: 3116361994 | I82: larocapublicidad.cali@gmail.com | J82: GASTO
A83: LEANDRO ANTONIO POPAYAN MELO | B83: 1113676974 | C83: LEANDRO | D83: ANTONIO | E83: POPAYAN | F83: MELO | G83: MZ B CASA 9 | H83: 3146846713 | J83: EMPLEADO GOTA
A84: istr | H84: 3153855247 | J84: COSTO
A85: LEIDY KARINA HURTADO | B85: 1007616371 | C85: LEIDY | D85: KARINA | E85: HURTADO | G85: CR 10 1A 57 | H85: 3168609680 | J85: EMPLEADO
A86: LM AUTOPARTS MOTORS SAS | B86: 901540026 | G86: CL 6 CR 8 | H86: 3117083212 | J86: GASTO
A87: LOS PAISAS MEGAFRUVER | B87: 1118285774 | G87: CL 7 9 34 | H87: 3013490273 | J87: COSTO
A88: =CONCATENATE(C88," ",D88," ",E88," ",F88) -> LUIS A CACERES MEZA | B88: 13254363 | C88: LUIS | D88: A | E88: CACERES | F88: MEZA | G88: CL 29 22 04 | H88: 2549029 | J88: EMPLEADO
A89: =CONCATENATE(C89," ",D89," ",E89," ",F89) -> LUIS ALBERTO MUÑOZ JARAMILLO | B89: 94470288 | C89: LUIS | D89: ALBERTO | E89: MUÑOZ | F89: JARAMILLO | G89: CL 3C 9 16 CABUYAL | H89: 3217848177 | J89: EMPLEADO
A90: MAKRO GASEOSAS SAS | B90: 901271654 | G90: CR 25 CL 26 ESQ | H90: 2844342 | J90: GASTO LOCAL
A91: MAYFENIX | B91: 94303748 | C91: MAYER | D91: ARLEY | E91: PALMA | F91: CAMPO | G91: CR 15 11 111 | H91: 3114099121 | J91: GASTO
A92: MEGA FRUVER LA FINCA 2 | G92: CR 4 CL 7 ESQ | H92: 3126147934 | J92: COSTO
A93: MERCAFRUVER EL MAYORISTA | B93: 14695845 | C93: EDELMIRA | E93: MORALES | F93: ACOSTA | G93: ST 1 MZ 19 VILLAMARINA | H93: 3215223609 | J93: COSTO
A94: MERCAPAVA SA | B94: 815002459 | C94: NO TIENE | D94: NO TIENE | E94: NO TIENE | F94: NO TIENE | G94: CL 7 12 03 | H94: 3136831049 | J94: COSTO
A95: METAL ACRILATO SA | B95: 811012912 | G95: KM 27 | H95: 4443153 | J95: GASTO
A96: MULTIREMATES | B96: 43795013 | G96: CR 11 6 62 | J96: GASTO
A97: MUNDIAL DE SEGUROS | J97: SOAT
A98: MUNDO LED ILUMINACION SAS | B98: 900663051 | G98: CR 25 30 56 | J98: GASTO
A99: MUTIREMATES | B99: 43795013 | G99: CR 11 6 620 | J99: GASTO
A100: mys inventarios | J100: GASTO
...
